{
  "Data_Archive": {
    "1": {
      "app": "LineMonitoring",
      "class": "line_monitoring",
      "method": "sensorActivity",
      "data": {
        "Sensor_id": 1,
        "active": false,
        "Tile_Kind": 1,
        "time": "21-10-09 17:25:15"
      }
    },
    "2": {
      "app": "LineMonitoring",
      "class": "line_monitoring",
      "method": "sensorActivity",
      "data": {
        "Sensor_id": 12,
        "active": false,
        "Tile_Kind": 1,
        "time": "21-05-12 15:44:54"
      }
    },
    "3": {
      "app": "LineMonitoring",
      "class": "line_monitoring",
      "method": "sensorActivity",
      "data": {
        "Sensor_id": 7,
        "active": false,
        "Tile_Kind": 1,
        "time": "21-05-12 15:44:52"
      }
    },
    "4": {
      "app": "LineMonitoring",
      "class": "line_monitoring",
      "method": "sensorActivity",
      "data": {
        "Sensor_id": 8,
        "active": false,
        "Tile_Kind": 1,
        "time": "21-10-10 16:11:06"
      }
    },
    "5": {
      "app": "LineMonitoring",
      "class": "line_monitoring",
      "method": "sensorActivity",
      "data": {
        "Sensor_id": 13,
        "active": false,
        "Tile_Kind": 1,
        "time": "21-05-12 15:39:39"
      }
    },
    "6": {
      "app": "LineMonitoring",
      "class": "line_monitoring",
      "method": "sensorActivity",
      "data": {
        "Sensor_id": 9,
        "active": false,
        "Tile_Kind": 1,
        "time": "21-05-12 15:44:46"
      }
    },
    "7": {
      "app": "LineMonitoring",
      "class": "line_monitoring",
      "method": "sensorActivity",
      "data": {
        "Sensor_id": 6,
        "active": false,
        "Tile_Kind": 1,
        "time": "21-05-21 14:19:56"
      }
    },
    "8": {
      "app": "LineMonitoring",
      "class": "line_monitoring",
      "method": "new_log",
      "data": {
        "Sensor_id": 8,
        "AbsTime": 26000,
        "counter": 1,
        "Tile_Kind": 1,
        "Motor_Speed": 100,
        "start_time": "21-10-11 23:00:37"
      }
    },
    "9": {
      "app": "LineMonitoring",
      "class": "line_monitoring",
      "method": "sensorActivity",
      "data": {
        "Sensor_id": 8,
        "active": true,
        "Tile_Kind": 1,
        "time": "21-10-11 23:00:37"
      }
    },
    "10": {
      "app": "LineMonitoring",
      "class": "line_monitoring",
      "method": "new_log",
      "data": {
        "Sensor_id": 1,
        "AbsTime": 1000,
        "counter": 1,
        "Tile_Kind": 1,
        "Motor_Speed": 100,
        "start_time": "21-10-11 23:00:37"
      }
    },
    "11": {
      "app": "LineMonitoring",
      "class": "line_monitoring",
      "method": "sensorActivity",
      "data": {
        "Sensor_id": 1,
        "active": true,
        "Tile_Kind": 1,
        "time": "21-10-11 23:00:37"
      }
    },
    "12": {
      "app": "LineMonitoring",
      "class": "line_monitoring",
      "method": "new_log",
      "data": {
        "Sensor_id": 1,
        "AbsTime": 1000,
        "counter": 1,
        "Tile_Kind": 1,
        "Motor_Speed": 100,
        "start_time": "21-10-11 23:00:38"
      }
    },
    "13": {
      "app": "LineMonitoring",
      "class": "line_monitoring",
      "method": "new_log",
      "data": {
        "Sensor_id": 1,
        "AbsTime": 1000,
        "counter": 1,
        "Tile_Kind": 1,
        "Motor_Speed": 100,
        "start_time": "21-10-11 23:00:38"
      }
    },
    "14": {
      "app": "LineMonitoring",
      "class": "line_monitoring",
      "method": "new_log",
      "data": {
        "Sensor_id": 1,
        "AbsTime": 1000,
        "counter": 1,
        "Tile_Kind": 1,
        "Motor_Speed": 100,
        "start_time": "21-10-11 23:00:38"
      }
    },
    "15": {
      "app": "LineMonitoring",
      "class": "line_monitoring",
      "method": "new_log",
      "data": {
        "Sensor_id": 1,
        "AbsTime": 1000,
        "counter": 1,
        "Tile_Kind": 1,
        "Motor_Speed": 100,
        "start_time": "21-10-11 23:00:38"
      }
    },
    "16": {
      "app": "LineMonitoring",
      "class": "line_monitoring",
      "method": "new_log",
      "data": {
        "Sensor_id": 1,
        "AbsTime": 1000,
        "counter": 1,
        "Tile_Kind": 1,
        "Motor_Speed": 100,
        "start_time": "21-10-11 23:00:38"
      }
    },
    "17": {
      "app": "LineMonitoring",
      "class": "line_monitoring",
      "method": "new_log",
      "data": {
        "Sensor_id": 1,
        "AbsTime": 1000,
        "counter": 1,
        "Tile_Kind": 1,
        "Motor_Speed": 100,
        "start_time": "21-10-11 23:00:38"
      }
    },
    "18": {
      "app": "LineMonitoring",
      "class": "line_monitoring",
      "method": "new_log",
      "data": {
        "Sensor_id": 1,
        "AbsTime": 1000,
        "counter": 1,
        "Tile_Kind": 1,
        "Motor_Speed": 100,
        "start_time": "21-10-11 23:00:38"
      }
    },
    "19": {
      "app": "LineMonitoring",
      "class": "line_monitoring",
      "method": "new_log",
      "data": {
        "Sensor_id": 1,
        "AbsTime": 1000,
        "counter": 1,
        "Tile_Kind": 1,
        "Motor_Speed": 100,
        "start_time": "21-10-11 23:00:38"
      }
    },
    "20": {
      "app": "LineMonitoring",
      "class": "line_monitoring",
      "method": "new_log",
      "data": {
        "Sensor_id": 1,
        "AbsTime": 1000,
        "counter": 1,
        "Tile_Kind": 1,
        "Motor_Speed": 100,
        "start_time": "21-10-11 23:00:38"
      }
    },
    "21": {
      "app": "LineMonitoring",
      "class": "line_monitoring",
      "method": "new_log",
      "data": {
        "Sensor_id": 1,
        "AbsTime": 1000,
        "counter": 1,
        "Tile_Kind": 1,
        "Motor_Speed": 100,
        "start_time": "21-10-11 23:00:38"
      }
    },
    "22": {
      "app": "LineMonitoring",
      "class": "line_monitoring",
      "method": "new_log",
      "data": {
        "Sensor_id": 1,
        "AbsTime": 1000,
        "counter": 1,
        "Tile_Kind": 1,
        "Motor_Speed": 100,
        "start_time": "21-10-11 23:00:38"
      }
    },
    "23": {
      "app": "LineMonitoring",
      "class": "line_monitoring",
      "method": "new_log",
      "data": {
        "Sensor_id": 1,
        "AbsTime": 1000,
        "counter": 1,
        "Tile_Kind": 1,
        "Motor_Speed": 100,
        "start_time": "21-10-11 23:00:38"
      }
    },
    "24": {
      "app": "LineMonitoring",
      "class": "line_monitoring",
      "method": "new_log",
      "data": {
        "Sensor_id": 1,
        "AbsTime": 1000,
        "counter": 1,
        "Tile_Kind": 1,
        "Motor_Speed": 100,
        "start_time": "21-10-11 23:00:38"
      }
    },
    "25": {
      "app": "LineMonitoring",
      "class": "line_monitoring",
      "method": "new_log",
      "data": {
        "Sensor_id": 1,
        "AbsTime": 1000,
        "counter": 1,
        "Tile_Kind": 1,
        "Motor_Speed": 100,
        "start_time": "21-10-11 23:00:39"
      }
    },
    "26": {
      "app": "LineMonitoring",
      "class": "line_monitoring",
      "method": "new_log",
      "data": {
        "Sensor_id": 1,
        "AbsTime": 1000,
        "counter": 1,
        "Tile_Kind": 1,
        "Motor_Speed": 100,
        "start_time": "21-10-11 23:00:39"
      }
    },
    "27": {
      "app": "LineMonitoring",
      "class": "line_monitoring",
      "method": "new_log",
      "data": {
        "Sensor_id": 1,
        "AbsTime": 1000,
        "counter": 1,
        "Tile_Kind": 1,
        "Motor_Speed": 100,
        "start_time": "21-10-11 23:00:39"
      }
    },
    "28": {
      "app": "LineMonitoring",
      "class": "line_monitoring",
      "method": "new_log",
      "data": {
        "Sensor_id": 1,
        "AbsTime": 1000,
        "counter": 1,
        "Tile_Kind": 1,
        "Motor_Speed": 100,
        "start_time": "21-10-11 23:00:39"
      }
    },
    "29": {
      "app": "LineMonitoring",
      "class": "line_monitoring",
      "method": "new_log",
      "data": {
        "Sensor_id": 1,
        "AbsTime": 1000,
        "counter": 1,
        "Tile_Kind": 1,
        "Motor_Speed": 100,
        "start_time": "21-10-11 23:00:39"
      }
    },
    "30": {
      "app": "LineMonitoring",
      "class": "line_monitoring",
      "method": "new_log",
      "data": {
        "Sensor_id": 1,
        "AbsTime": 1000,
        "counter": 1,
        "Tile_Kind": 1,
        "Motor_Speed": 100,
        "start_time": "21-10-11 23:00:39"
      }
    },
    "31": {
      "app": "LineMonitoring",
      "class": "line_monitoring",
      "method": "new_log",
      "data": {
        "Sensor_id": 1,
        "AbsTime": 1000,
        "counter": 1,
        "Tile_Kind": 1,
        "Motor_Speed": 100,
        "start_time": "21-10-11 23:00:39"
      }
    },
    "32": {
      "app": "LineMonitoring",
      "class": "line_monitoring",
      "method": "new_log",
      "data": {
        "Sensor_id": 1,
        "AbsTime": 1000,
        "counter": 1,
        "Tile_Kind": 1,
        "Motor_Speed": 100,
        "start_time": "21-10-11 23:00:39"
      }
    },
    "33": {
      "app": "LineMonitoring",
      "class": "line_monitoring",
      "method": "new_log",
      "data": {
        "Sensor_id": 8,
        "AbsTime": 26000,
        "counter": 1,
        "Tile_Kind": 1,
        "Motor_Speed": 100,
        "start_time": "21-10-11 23:00:39"
      }
    },
    "34": {
      "app": "LineMonitoring",
      "class": "line_monitoring",
      "method": "new_log",
      "data": {
        "Sensor_id": 8,
        "AbsTime": 26000,
        "counter": 1,
        "Tile_Kind": 1,
        "Motor_Speed": 100,
        "start_time": "21-10-11 23:00:39"
      }
    },
    "35": {
      "app": "LineMonitoring",
      "class": "line_monitoring",
      "method": "new_log",
      "data": {
        "Sensor_id": 8,
        "AbsTime": 26000,
        "counter": 1,
        "Tile_Kind": 1,
        "Motor_Speed": 100,
        "start_time": "21-10-11 23:00:39"
      }
    },
    "36": {
      "app": "LineMonitoring",
      "class": "line_monitoring",
      "method": "new_log",
      "data": {
        "Sensor_id": 8,
        "AbsTime": 26000,
        "counter": 1,
        "Tile_Kind": 1,
        "Motor_Speed": 100,
        "start_time": "21-10-11 23:00:39"
      }
    },
    "37": {
      "app": "LineMonitoring",
      "class": "line_monitoring",
      "method": "new_log",
      "data": {
        "Sensor_id": 8,
        "AbsTime": 26000,
        "counter": 1,
        "Tile_Kind": 1,
        "Motor_Speed": 100,
        "start_time": "21-10-11 23:00:39"
      }
    },
    "38": {
      "app": "LineMonitoring",
      "class": "line_monitoring",
      "method": "new_log",
      "data": {
        "Sensor_id": 8,
        "AbsTime": 26000,
        "counter": 1,
        "Tile_Kind": 1,
        "Motor_Speed": 100,
        "start_time": "21-10-11 23:00:39"
      }
    },
    "39": {
      "app": "LineMonitoring",
      "class": "line_monitoring",
      "method": "new_log",
      "data": {
        "Sensor_id": 8,
        "AbsTime": 13000,
        "counter": 1,
        "Tile_Kind": 1,
        "Motor_Speed": 100,
        "start_time": "21-10-11 23:00:39"
      }
    },
    "40": {
      "app": "LineMonitoring",
      "class": "line_monitoring",
      "method": "new_log",
      "data": {
        "Sensor_id": 8,
        "AbsTime": 26000,
        "counter": 1,
        "Tile_Kind": 1,
        "Motor_Speed": 100,
        "start_time": "21-10-11 23:00:39"
      }
    },
    "41": {
      "app": "LineMonitoring",
      "class": "line_monitoring",
      "method": "new_log",
      "data": {
        "Sensor_id": 8,
        "AbsTime": 13000,
        "counter": 1,
        "Tile_Kind": 1,
        "Motor_Speed": 100,
        "start_time": "21-10-11 23:00:39"
      }
    },
    "42": {
      "app": "LineMonitoring",
      "class": "line_monitoring",
      "method": "new_log",
      "data": {
        "Sensor_id": 8,
        "AbsTime": 26000,
        "counter": 1,
        "Tile_Kind": 1,
        "Motor_Speed": 100,
        "start_time": "21-10-11 23:00:39"
      }
    },
    "43": {
      "app": "LineMonitoring",
      "class": "line_monitoring",
      "method": "new_log",
      "data": {
        "Sensor_id": 8,
        "AbsTime": 13000,
        "counter": 1,
        "Tile_Kind": 1,
        "Motor_Speed": 100,
        "start_time": "21-10-11 23:00:39"
      }
    },
    "44": {
      "app": "LineMonitoring",
      "class": "line_monitoring",
      "method": "new_log",
      "data": {
        "Sensor_id": 8,
        "AbsTime": 26000,
        "counter": 1,
        "Tile_Kind": 1,
        "Motor_Speed": 100,
        "start_time": "21-10-11 23:00:39"
      }
    },
    "45": {
      "app": "LineMonitoring",
      "class": "line_monitoring",
      "method": "new_log",
      "data": {
        "Sensor_id": 1,
        "AbsTime": 1000,
        "counter": 1,
        "Tile_Kind": 1,
        "Motor_Speed": 100,
        "start_time": "21-10-11 23:00:39"
      }
    },
    "46": {
      "app": "LineMonitoring",
      "class": "line_monitoring",
      "method": "new_log",
      "data": {
        "Sensor_id": 1,
        "AbsTime": 1000,
        "counter": 1,
        "Tile_Kind": 1,
        "Motor_Speed": 100,
        "start_time": "21-10-11 23:00:39"
      }
    },
    "47": {
      "app": "LineMonitoring",
      "class": "line_monitoring",
      "method": "new_log",
      "data": {
        "Sensor_id": 1,
        "AbsTime": 1000,
        "counter": 1,
        "Tile_Kind": 1,
        "Motor_Speed": 100,
        "start_time": "21-10-11 23:00:39"
      }
    },
    "48": {
      "app": "LineMonitoring",
      "class": "line_monitoring",
      "method": "new_log",
      "data": {
        "Sensor_id": 1,
        "AbsTime": 1000,
        "counter": 1,
        "Tile_Kind": 1,
        "Motor_Speed": 100,
        "start_time": "21-10-11 23:00:39"
      }
    },
    "49": {
      "app": "LineMonitoring",
      "class": "line_monitoring",
      "method": "new_log",
      "data": {
        "Sensor_id": 1,
        "AbsTime": 1000,
        "counter": 1,
        "Tile_Kind": 1,
        "Motor_Speed": 100,
        "start_time": "21-10-11 23:00:40"
      }
    },
    "50": {
      "app": "LineMonitoring",
      "class": "line_monitoring",
      "method": "new_log",
      "data": {
        "Sensor_id": 1,
        "AbsTime": 1000,
        "counter": 1,
        "Tile_Kind": 1,
        "Motor_Speed": 100,
        "start_time": "21-10-11 23:00:40"
      }
    },
    "51": {
      "app": "LineMonitoring",
      "class": "line_monitoring",
      "method": "new_log",
      "data": {
        "Sensor_id": 1,
        "AbsTime": 1000,
        "counter": 1,
        "Tile_Kind": 1,
        "Motor_Speed": 100,
        "start_time": "21-10-11 23:00:40"
      }
    },
    "52": {
      "app": "LineMonitoring",
      "class": "line_monitoring",
      "method": "new_log",
      "data": {
        "Sensor_id": 1,
        "AbsTime": 1000,
        "counter": 1,
        "Tile_Kind": 1,
        "Motor_Speed": 100,
        "start_time": "21-10-11 23:00:40"
      }
    },
    "53": {
      "app": "LineMonitoring",
      "class": "line_monitoring",
      "method": "new_log",
      "data": {
        "Sensor_id": 1,
        "AbsTime": 1000,
        "counter": 1,
        "Tile_Kind": 1,
        "Motor_Speed": 100,
        "start_time": "21-10-11 23:00:40"
      }
    },
    "54": {
      "app": "LineMonitoring",
      "class": "line_monitoring",
      "method": "new_log",
      "data": {
        "Sensor_id": 1,
        "AbsTime": 1000,
        "counter": 1,
        "Tile_Kind": 1,
        "Motor_Speed": 100,
        "start_time": "21-10-11 23:00:40"
      }
    },
    "55": {
      "app": "LineMonitoring",
      "class": "line_monitoring",
      "method": "new_log",
      "data": {
        "Sensor_id": 1,
        "AbsTime": 1000,
        "counter": 1,
        "Tile_Kind": 1,
        "Motor_Speed": 100,
        "start_time": "21-10-11 23:00:40"
      }
    },
    "56": {
      "app": "LineMonitoring",
      "class": "line_monitoring",
      "method": "new_log",
      "data": {
        "Sensor_id": 1,
        "AbsTime": 1000,
        "counter": 1,
        "Tile_Kind": 1,
        "Motor_Speed": 100,
        "start_time": "21-10-11 23:00:40"
      }
    },
    "57": {
      "app": "LineMonitoring",
      "class": "line_monitoring",
      "method": "new_log",
      "data": {
        "Sensor_id": 1,
        "AbsTime": 1000,
        "counter": 1,
        "Tile_Kind": 1,
        "Motor_Speed": 100,
        "start_time": "21-10-11 23:00:40"
      }
    },
    "58": {
      "app": "LineMonitoring",
      "class": "line_monitoring",
      "method": "new_log",
      "data": {
        "Sensor_id": 1,
        "AbsTime": 1000,
        "counter": 1,
        "Tile_Kind": 1,
        "Motor_Speed": 100,
        "start_time": "21-10-11 23:00:40"
      }
    },
    "59": {
      "app": "LineMonitoring",
      "class": "line_monitoring",
      "method": "new_log",
      "data": {
        "Sensor_id": 1,
        "AbsTime": 1000,
        "counter": 1,
        "Tile_Kind": 1,
        "Motor_Speed": 100,
        "start_time": "21-10-11 23:00:40"
      }
    },
    "60": {
      "app": "LineMonitoring",
      "class": "line_monitoring",
      "method": "new_log",
      "data": {
        "Sensor_id": 1,
        "AbsTime": 1000,
        "counter": 1,
        "Tile_Kind": 1,
        "Motor_Speed": 100,
        "start_time": "21-10-11 23:00:40"
      }
    },
    "61": {
      "app": "LineMonitoring",
      "class": "line_monitoring",
      "method": "new_log",
      "data": {
        "Sensor_id": 1,
        "AbsTime": 1000,
        "counter": 1,
        "Tile_Kind": 1,
        "Motor_Speed": 100,
        "start_time": "21-10-11 23:00:40"
      }
    },
    "62": {
      "app": "LineMonitoring",
      "class": "line_monitoring",
      "method": "new_log",
      "data": {
        "Sensor_id": 1,
        "AbsTime": 1000,
        "counter": 1,
        "Tile_Kind": 1,
        "Motor_Speed": 100,
        "start_time": "21-10-11 23:00:40"
      }
    },
    "63": {
      "app": "LineMonitoring",
      "class": "line_monitoring",
      "method": "new_log",
      "data": {
        "Sensor_id": 1,
        "AbsTime": 1000,
        "counter": 1,
        "Tile_Kind": 1,
        "Motor_Speed": 100,
        "start_time": "21-10-11 23:00:40"
      }
    },
    "64": {
      "app": "LineMonitoring",
      "class": "line_monitoring",
      "method": "new_log",
      "data": {
        "Sensor_id": 1,
        "AbsTime": 1000,
        "counter": 1,
        "Tile_Kind": 1,
        "Motor_Speed": 100,
        "start_time": "21-10-11 23:00:40"
      }
    },
    "65": {
      "app": "LineMonitoring",
      "class": "line_monitoring",
      "method": "new_log",
      "data": {
        "Sensor_id": 1,
        "AbsTime": 1000,
        "counter": 1,
        "Tile_Kind": 1,
        "Motor_Speed": 100,
        "start_time": "21-10-11 23:00:40"
      }
    },
    "66": {
      "app": "LineMonitoring",
      "class": "line_monitoring",
      "method": "new_log",
      "data": {
        "Sensor_id": 1,
        "AbsTime": 1000,
        "counter": 1,
        "Tile_Kind": 1,
        "Motor_Speed": 100,
        "start_time": "21-10-11 23:00:40"
      }
    },
    "67": {
      "app": "LineMonitoring",
      "class": "line_monitoring",
      "method": "new_log",
      "data": {
        "Sensor_id": 1,
        "AbsTime": 1000,
        "counter": 1,
        "Tile_Kind": 1,
        "Motor_Speed": 100,
        "start_time": "21-10-11 23:00:40"
      }
    },
    "68": {
      "app": "LineMonitoring",
      "class": "line_monitoring",
      "method": "new_log",
      "data": {
        "Sensor_id": 1,
        "AbsTime": 1000,
        "counter": 1,
        "Tile_Kind": 1,
        "Motor_Speed": 100,
        "start_time": "21-10-11 23:00:40"
      }
    },
    "69": {
      "app": "LineMonitoring",
      "class": "line_monitoring",
      "method": "new_log",
      "data": {
        "Sensor_id": 1,
        "AbsTime": 1000,
        "counter": 1,
        "Tile_Kind": 1,
        "Motor_Speed": 100,
        "start_time": "21-10-11 23:00:40"
      }
    },
    "70": {
      "app": "LineMonitoring",
      "class": "line_monitoring",
      "method": "new_log",
      "data": {
        "Sensor_id": 1,
        "AbsTime": 1000,
        "counter": 1,
        "Tile_Kind": 1,
        "Motor_Speed": 100,
        "start_time": "21-10-11 23:00:40"
      }
    },
    "71": {
      "app": "LineMonitoring",
      "class": "line_monitoring",
      "method": "new_log",
      "data": {
        "Sensor_id": 1,
        "AbsTime": 1000,
        "counter": 1,
        "Tile_Kind": 1,
        "Motor_Speed": 100,
        "start_time": "21-10-11 23:00:40"
      }
    },
    "72": {
      "app": "LineMonitoring",
      "class": "line_monitoring",
      "method": "new_log",
      "data": {
        "Sensor_id": 1,
        "AbsTime": 1000,
        "counter": 1,
        "Tile_Kind": 1,
        "Motor_Speed": 100,
        "start_time": "21-10-11 23:00:40"
      }
    },
    "73": {
      "app": "LineMonitoring",
      "class": "line_monitoring",
      "method": "new_log",
      "data": {
        "Sensor_id": 1,
        "AbsTime": 1000,
        "counter": 1,
        "Tile_Kind": 1,
        "Motor_Speed": 100,
        "start_time": "21-10-11 23:00:41"
      }
    },
    "74": {
      "app": "LineMonitoring",
      "class": "line_monitoring",
      "method": "new_log",
      "data": {
        "Sensor_id": 1,
        "AbsTime": 1000,
        "counter": 1,
        "Tile_Kind": 1,
        "Motor_Speed": 100,
        "start_time": "21-10-11 23:00:41"
      }
    },
    "75": {
      "app": "LineMonitoring",
      "class": "line_monitoring",
      "method": "new_log",
      "data": {
        "Sensor_id": 1,
        "AbsTime": 1000,
        "counter": 1,
        "Tile_Kind": 1,
        "Motor_Speed": 100,
        "start_time": "21-10-11 23:00:41"
      }
    },
    "76": {
      "app": "LineMonitoring",
      "class": "line_monitoring",
      "method": "new_log",
      "data": {
        "Sensor_id": 1,
        "AbsTime": 1000,
        "counter": 1,
        "Tile_Kind": 1,
        "Motor_Speed": 100,
        "start_time": "21-10-11 23:00:41"
      }
    },
    "77": {
      "app": "LineMonitoring",
      "class": "line_monitoring",
      "method": "new_log",
      "data": {
        "Sensor_id": 1,
        "AbsTime": 1000,
        "counter": 1,
        "Tile_Kind": 1,
        "Motor_Speed": 100,
        "start_time": "21-10-11 23:00:41"
      }
    },
    "78": {
      "app": "LineMonitoring",
      "class": "line_monitoring",
      "method": "new_log",
      "data": {
        "Sensor_id": 1,
        "AbsTime": 1000,
        "counter": 1,
        "Tile_Kind": 1,
        "Motor_Speed": 100,
        "start_time": "21-10-11 23:00:41"
      }
    },
    "79": {
      "app": "LineMonitoring",
      "class": "line_monitoring",
      "method": "new_log",
      "data": {
        "Sensor_id": 1,
        "AbsTime": 1000,
        "counter": 1,
        "Tile_Kind": 1,
        "Motor_Speed": 100,
        "start_time": "21-10-11 23:00:41"
      }
    },
    "80": {
      "app": "LineMonitoring",
      "class": "line_monitoring",
      "method": "new_log",
      "data": {
        "Sensor_id": 1,
        "AbsTime": 1000,
        "counter": 1,
        "Tile_Kind": 1,
        "Motor_Speed": 100,
        "start_time": "21-10-11 23:00:41"
      }
    },
    "81": {
      "app": "LineMonitoring",
      "class": "line_monitoring",
      "method": "new_log",
      "data": {
        "Sensor_id": 1,
        "AbsTime": 1000,
        "counter": 1,
        "Tile_Kind": 1,
        "Motor_Speed": 100,
        "start_time": "21-10-11 23:00:41"
      }
    },
    "82": {
      "app": "LineMonitoring",
      "class": "line_monitoring",
      "method": "new_log",
      "data": {
        "Sensor_id": 1,
        "AbsTime": 1000,
        "counter": 1,
        "Tile_Kind": 1,
        "Motor_Speed": 100,
        "start_time": "21-10-11 23:00:41"
      }
    },
    "83": {
      "app": "LineMonitoring",
      "class": "line_monitoring",
      "method": "new_log",
      "data": {
        "Sensor_id": 1,
        "AbsTime": 1000,
        "counter": 1,
        "Tile_Kind": 1,
        "Motor_Speed": 100,
        "start_time": "21-10-11 23:00:41"
      }
    },
    "84": {
      "app": "LineMonitoring",
      "class": "line_monitoring",
      "method": "new_log",
      "data": {
        "Sensor_id": 1,
        "AbsTime": 1000,
        "counter": 1,
        "Tile_Kind": 1,
        "Motor_Speed": 100,
        "start_time": "21-10-11 23:00:41"
      }
    },
    "85": {
      "app": "LineMonitoring",
      "class": "line_monitoring",
      "method": "new_log",
      "data": {
        "Sensor_id": 1,
        "AbsTime": 1000,
        "counter": 1,
        "Tile_Kind": 1,
        "Motor_Speed": 100,
        "start_time": "21-10-11 23:00:41"
      }
    },
    "86": {
      "app": "LineMonitoring",
      "class": "line_monitoring",
      "method": "new_log",
      "data": {
        "Sensor_id": 1,
        "AbsTime": 1000,
        "counter": 1,
        "Tile_Kind": 1,
        "Motor_Speed": 100,
        "start_time": "21-10-11 23:00:41"
      }
    },
    "87": {
      "app": "LineMonitoring",
      "class": "line_monitoring",
      "method": "new_log",
      "data": {
        "Sensor_id": 1,
        "AbsTime": 1000,
        "counter": 1,
        "Tile_Kind": 1,
        "Motor_Speed": 100,
        "start_time": "21-10-11 23:00:41"
      }
    },
    "88": {
      "app": "LineMonitoring",
      "class": "line_monitoring",
      "method": "new_log",
      "data": {
        "Sensor_id": 1,
        "AbsTime": 1000,
        "counter": 1,
        "Tile_Kind": 1,
        "Motor_Speed": 100,
        "start_time": "21-10-11 23:00:41"
      }
    },
    "89": {
      "app": "LineMonitoring",
      "class": "line_monitoring",
      "method": "new_log",
      "data": {
        "Sensor_id": 1,
        "AbsTime": 1000,
        "counter": 1,
        "Tile_Kind": 1,
        "Motor_Speed": 100,
        "start_time": "21-10-11 23:00:41"
      }
    },
    "90": {
      "app": "LineMonitoring",
      "class": "line_monitoring",
      "method": "new_log",
      "data": {
        "Sensor_id": 1,
        "AbsTime": 1000,
        "counter": 1,
        "Tile_Kind": 1,
        "Motor_Speed": 100,
        "start_time": "21-10-11 23:00:41"
      }
    },
    "91": {
      "app": "LineMonitoring",
      "class": "line_monitoring",
      "method": "new_log",
      "data": {
        "Sensor_id": 1,
        "AbsTime": 1000,
        "counter": 1,
        "Tile_Kind": 1,
        "Motor_Speed": 100,
        "start_time": "21-10-11 23:00:41"
      }
    },
    "92": {
      "app": "LineMonitoring",
      "class": "line_monitoring",
      "method": "new_log",
      "data": {
        "Sensor_id": 1,
        "AbsTime": 1000,
        "counter": 1,
        "Tile_Kind": 1,
        "Motor_Speed": 100,
        "start_time": "21-10-11 23:00:41"
      }
    },
    "93": {
      "app": "LineMonitoring",
      "class": "line_monitoring",
      "method": "new_log",
      "data": {
        "Sensor_id": 1,
        "AbsTime": 1000,
        "counter": 1,
        "Tile_Kind": 1,
        "Motor_Speed": 100,
        "start_time": "21-10-11 23:00:41"
      }
    },
    "94": {
      "app": "LineMonitoring",
      "class": "line_monitoring",
      "method": "new_log",
      "data": {
        "Sensor_id": 1,
        "AbsTime": 1000,
        "counter": 1,
        "Tile_Kind": 1,
        "Motor_Speed": 100,
        "start_time": "21-10-11 23:00:42"
      }
    },
    "95": {
      "app": "LineMonitoring",
      "class": "line_monitoring",
      "method": "new_log",
      "data": {
        "Sensor_id": 1,
        "AbsTime": 1000,
        "counter": 1,
        "Tile_Kind": 1,
        "Motor_Speed": 100,
        "start_time": "21-10-11 23:00:42"
      }
    },
    "96": {
      "app": "LineMonitoring",
      "class": "line_monitoring",
      "method": "new_log",
      "data": {
        "Sensor_id": 1,
        "AbsTime": 1000,
        "counter": 1,
        "Tile_Kind": 1,
        "Motor_Speed": 100,
        "start_time": "21-10-11 23:00:42"
      }
    },
    "97": {
      "app": "LineMonitoring",
      "class": "line_monitoring",
      "method": "new_log",
      "data": {
        "Sensor_id": 1,
        "AbsTime": 1000,
        "counter": 1,
        "Tile_Kind": 1,
        "Motor_Speed": 100,
        "start_time": "21-10-11 23:00:42"
      }
    },
    "98": {
      "app": "LineMonitoring",
      "class": "line_monitoring",
      "method": "new_log",
      "data": {
        "Sensor_id": 1,
        "AbsTime": 1000,
        "counter": 1,
        "Tile_Kind": 1,
        "Motor_Speed": 100,
        "start_time": "21-10-11 23:00:42"
      }
    },
    "99": {
      "app": "LineMonitoring",
      "class": "line_monitoring",
      "method": "new_log",
      "data": {
        "Sensor_id": 1,
        "AbsTime": 1000,
        "counter": 1,
        "Tile_Kind": 1,
        "Motor_Speed": 100,
        "start_time": "21-10-11 23:00:42"
      }
    },
    "100": {
      "app": "LineMonitoring",
      "class": "line_monitoring",
      "method": "new_log",
      "data": {
        "Sensor_id": 1,
        "AbsTime": 1000,
        "counter": 1,
        "Tile_Kind": 1,
        "Motor_Speed": 100,
        "start_time": "21-10-11 23:00:42"
      }
    },
    "101": {
      "app": "LineMonitoring",
      "class": "line_monitoring",
      "method": "new_log",
      "data": {
        "Sensor_id": 1,
        "AbsTime": 1000,
        "counter": 1,
        "Tile_Kind": 1,
        "Motor_Speed": 100,
        "start_time": "21-10-11 23:00:42"
      }
    },
    "102": {
      "app": "LineMonitoring",
      "class": "line_monitoring",
      "method": "new_log",
      "data": {
        "Sensor_id": 1,
        "AbsTime": 1000,
        "counter": 1,
        "Tile_Kind": 1,
        "Motor_Speed": 100,
        "start_time": "21-10-11 23:00:42"
      }
    },
    "103": {
      "app": "LineMonitoring",
      "class": "line_monitoring",
      "method": "new_log",
      "data": {
        "Sensor_id": 1,
        "AbsTime": 1000,
        "counter": 1,
        "Tile_Kind": 1,
        "Motor_Speed": 100,
        "start_time": "21-10-11 23:00:42"
      }
    },
    "104": {
      "app": "LineMonitoring",
      "class": "line_monitoring",
      "method": "new_log",
      "data": {
        "Sensor_id": 1,
        "AbsTime": 1000,
        "counter": 1,
        "Tile_Kind": 1,
        "Motor_Speed": 100,
        "start_time": "21-10-11 23:00:42"
      }
    },
    "105": {
      "app": "LineMonitoring",
      "class": "line_monitoring",
      "method": "new_log",
      "data": {
        "Sensor_id": 1,
        "AbsTime": 1000,
        "counter": 1,
        "Tile_Kind": 1,
        "Motor_Speed": 100,
        "start_time": "21-10-11 23:00:42"
      }
    },
    "106": {
      "app": "LineMonitoring",
      "class": "line_monitoring",
      "method": "new_log",
      "data": {
        "Sensor_id": 1,
        "AbsTime": 1000,
        "counter": 1,
        "Tile_Kind": 1,
        "Motor_Speed": 100,
        "start_time": "21-10-11 23:00:42"
      }
    },
    "107": {
      "app": "LineMonitoring",
      "class": "line_monitoring",
      "method": "new_log",
      "data": {
        "Sensor_id": 1,
        "AbsTime": 1000,
        "counter": 1,
        "Tile_Kind": 1,
        "Motor_Speed": 100,
        "start_time": "21-10-11 23:00:42"
      }
    },
    "108": {
      "app": "LineMonitoring",
      "class": "line_monitoring",
      "method": "new_log",
      "data": {
        "Sensor_id": 1,
        "AbsTime": 1000,
        "counter": 1,
        "Tile_Kind": 1,
        "Motor_Speed": 100,
        "start_time": "21-10-11 23:00:42"
      }
    },
    "109": {
      "app": "LineMonitoring",
      "class": "line_monitoring",
      "method": "new_log",
      "data": {
        "Sensor_id": 1,
        "AbsTime": 1000,
        "counter": 1,
        "Tile_Kind": 1,
        "Motor_Speed": 100,
        "start_time": "21-10-11 23:00:42"
      }
    },
    "110": {
      "app": "LineMonitoring",
      "class": "line_monitoring",
      "method": "new_log",
      "data": {
        "Sensor_id": 1,
        "AbsTime": 1000,
        "counter": 1,
        "Tile_Kind": 1,
        "Motor_Speed": 100,
        "start_time": "21-10-11 23:00:42"
      }
    },
    "111": {
      "app": "LineMonitoring",
      "class": "line_monitoring",
      "method": "new_log",
      "data": {
        "Sensor_id": 1,
        "AbsTime": 1000,
        "counter": 1,
        "Tile_Kind": 1,
        "Motor_Speed": 100,
        "start_time": "21-10-11 23:00:42"
      }
    },
    "112": {
      "app": "LineMonitoring",
      "class": "line_monitoring",
      "method": "new_log",
      "data": {
        "Sensor_id": 1,
        "AbsTime": 1000,
        "counter": 1,
        "Tile_Kind": 1,
        "Motor_Speed": 100,
        "start_time": "21-10-11 23:00:42"
      }
    },
    "113": {
      "app": "LineMonitoring",
      "class": "line_monitoring",
      "method": "new_log",
      "data": {
        "Sensor_id": 1,
        "AbsTime": 1000,
        "counter": 1,
        "Tile_Kind": 1,
        "Motor_Speed": 100,
        "start_time": "21-10-11 23:00:42"
      }
    },
    "114": {
      "app": "LineMonitoring",
      "class": "line_monitoring",
      "method": "new_log",
      "data": {
        "Sensor_id": 1,
        "AbsTime": 1000,
        "counter": 1,
        "Tile_Kind": 1,
        "Motor_Speed": 100,
        "start_time": "21-10-11 23:00:42"
      }
    },
    "115": {
      "app": "LineMonitoring",
      "class": "line_monitoring",
      "method": "new_log",
      "data": {
        "Sensor_id": 1,
        "AbsTime": 1000,
        "counter": 1,
        "Tile_Kind": 1,
        "Motor_Speed": 100,
        "start_time": "21-10-11 23:00:42"
      }
    },
    "116": {
      "app": "LineMonitoring",
      "class": "line_monitoring",
      "method": "new_log",
      "data": {
        "Sensor_id": 1,
        "AbsTime": 1000,
        "counter": 1,
        "Tile_Kind": 1,
        "Motor_Speed": 100,
        "start_time": "21-10-11 23:00:42"
      }
    },
    "117": {
      "app": "LineMonitoring",
      "class": "line_monitoring",
      "method": "new_log",
      "data": {
        "Sensor_id": 1,
        "AbsTime": 1000,
        "counter": 1,
        "Tile_Kind": 1,
        "Motor_Speed": 100,
        "start_time": "21-10-11 23:00:42"
      }
    },
    "118": {
      "app": "LineMonitoring",
      "class": "line_monitoring",
      "method": "new_log",
      "data": {
        "Sensor_id": 1,
        "AbsTime": 1000,
        "counter": 1,
        "Tile_Kind": 1,
        "Motor_Speed": 100,
        "start_time": "21-10-11 23:00:42"
      }
    },
    "119": {
      "app": "LineMonitoring",
      "class": "line_monitoring",
      "method": "new_log",
      "data": {
        "Sensor_id": 1,
        "AbsTime": 1000,
        "counter": 1,
        "Tile_Kind": 1,
        "Motor_Speed": 100,
        "start_time": "21-10-11 23:00:42"
      }
    },
    "120": {
      "app": "LineMonitoring",
      "class": "line_monitoring",
      "method": "new_log",
      "data": {
        "Sensor_id": 1,
        "AbsTime": 1000,
        "counter": 1,
        "Tile_Kind": 1,
        "Motor_Speed": 100,
        "start_time": "21-10-11 23:00:42"
      }
    },
    "121": {
      "app": "LineMonitoring",
      "class": "line_monitoring",
      "method": "new_log",
      "data": {
        "Sensor_id": 1,
        "AbsTime": 1000,
        "counter": 1,
        "Tile_Kind": 1,
        "Motor_Speed": 100,
        "start_time": "21-10-11 23:00:42"
      }
    },
    "122": {
      "app": "LineMonitoring",
      "class": "line_monitoring",
      "method": "new_log",
      "data": {
        "Sensor_id": 1,
        "AbsTime": 1000,
        "counter": 1,
        "Tile_Kind": 1,
        "Motor_Speed": 100,
        "start_time": "21-10-11 23:00:42"
      }
    },
    "123": {
      "app": "LineMonitoring",
      "class": "line_monitoring",
      "method": "new_log",
      "data": {
        "Sensor_id": 1,
        "AbsTime": 1000,
        "counter": 1,
        "Tile_Kind": 1,
        "Motor_Speed": 100,
        "start_time": "21-10-11 23:00:42"
      }
    },
    "124": {
      "app": "LineMonitoring",
      "class": "line_monitoring",
      "method": "new_log",
      "data": {
        "Sensor_id": 1,
        "AbsTime": 1000,
        "counter": 1,
        "Tile_Kind": 1,
        "Motor_Speed": 100,
        "start_time": "21-10-11 23:00:42"
      }
    },
    "125": {
      "app": "LineMonitoring",
      "class": "line_monitoring",
      "method": "new_log",
      "data": {
        "Sensor_id": 1,
        "AbsTime": 1000,
        "counter": 1,
        "Tile_Kind": 1,
        "Motor_Speed": 100,
        "start_time": "21-10-11 23:00:43"
      }
    },
    "126": {
      "app": "LineMonitoring",
      "class": "line_monitoring",
      "method": "new_log",
      "data": {
        "Sensor_id": 1,
        "AbsTime": 1000,
        "counter": 1,
        "Tile_Kind": 1,
        "Motor_Speed": 100,
        "start_time": "21-10-11 23:00:43"
      }
    },
    "127": {
      "app": "LineMonitoring",
      "class": "line_monitoring",
      "method": "new_log",
      "data": {
        "Sensor_id": 1,
        "AbsTime": 1000,
        "counter": 1,
        "Tile_Kind": 1,
        "Motor_Speed": 100,
        "start_time": "21-10-11 23:00:43"
      }
    },
    "128": {
      "app": "LineMonitoring",
      "class": "line_monitoring",
      "method": "new_log",
      "data": {
        "Sensor_id": 1,
        "AbsTime": 1000,
        "counter": 1,
        "Tile_Kind": 1,
        "Motor_Speed": 100,
        "start_time": "21-10-11 23:00:43"
      }
    },
    "129": {
      "app": "LineMonitoring",
      "class": "line_monitoring",
      "method": "new_log",
      "data": {
        "Sensor_id": 1,
        "AbsTime": 1000,
        "counter": 1,
        "Tile_Kind": 1,
        "Motor_Speed": 100,
        "start_time": "21-10-11 23:00:43"
      }
    },
    "130": {
      "app": "LineMonitoring",
      "class": "line_monitoring",
      "method": "new_log",
      "data": {
        "Sensor_id": 1,
        "AbsTime": 1000,
        "counter": 1,
        "Tile_Kind": 1,
        "Motor_Speed": 100,
        "start_time": "21-10-11 23:00:43"
      }
    },
    "131": {
      "app": "LineMonitoring",
      "class": "line_monitoring",
      "method": "new_log",
      "data": {
        "Sensor_id": 1,
        "AbsTime": 1000,
        "counter": 1,
        "Tile_Kind": 1,
        "Motor_Speed": 100,
        "start_time": "21-10-11 23:00:43"
      }
    },
    "132": {
      "app": "LineMonitoring",
      "class": "line_monitoring",
      "method": "new_log",
      "data": {
        "Sensor_id": 1,
        "AbsTime": 1000,
        "counter": 1,
        "Tile_Kind": 1,
        "Motor_Speed": 100,
        "start_time": "21-10-11 23:00:43"
      }
    },
    "133": {
      "app": "LineMonitoring",
      "class": "line_monitoring",
      "method": "new_log",
      "data": {
        "Sensor_id": 1,
        "AbsTime": 1000,
        "counter": 1,
        "Tile_Kind": 1,
        "Motor_Speed": 100,
        "start_time": "21-10-11 23:00:43"
      }
    },
    "134": {
      "app": "LineMonitoring",
      "class": "line_monitoring",
      "method": "new_log",
      "data": {
        "Sensor_id": 1,
        "AbsTime": 1000,
        "counter": 1,
        "Tile_Kind": 1,
        "Motor_Speed": 100,
        "start_time": "21-10-11 23:00:43"
      }
    },
    "135": {
      "app": "LineMonitoring",
      "class": "line_monitoring",
      "method": "new_log",
      "data": {
        "Sensor_id": 1,
        "AbsTime": 1000,
        "counter": 1,
        "Tile_Kind": 1,
        "Motor_Speed": 100,
        "start_time": "21-10-11 23:00:43"
      }
    },
    "136": {
      "app": "LineMonitoring",
      "class": "line_monitoring",
      "method": "new_log",
      "data": {
        "Sensor_id": 1,
        "AbsTime": 1000,
        "counter": 1,
        "Tile_Kind": 1,
        "Motor_Speed": 100,
        "start_time": "21-10-11 23:00:43"
      }
    },
    "137": {
      "app": "LineMonitoring",
      "class": "line_monitoring",
      "method": "new_log",
      "data": {
        "Sensor_id": 1,
        "AbsTime": 1000,
        "counter": 1,
        "Tile_Kind": 1,
        "Motor_Speed": 100,
        "start_time": "21-10-11 23:00:43"
      }
    },
    "138": {
      "app": "LineMonitoring",
      "class": "line_monitoring",
      "method": "new_log",
      "data": {
        "Sensor_id": 1,
        "AbsTime": 1000,
        "counter": 1,
        "Tile_Kind": 1,
        "Motor_Speed": 100,
        "start_time": "21-10-11 23:00:43"
      }
    },
    "139": {
      "app": "LineMonitoring",
      "class": "line_monitoring",
      "method": "new_log",
      "data": {
        "Sensor_id": 1,
        "AbsTime": 1000,
        "counter": 1,
        "Tile_Kind": 1,
        "Motor_Speed": 100,
        "start_time": "21-10-11 23:00:43"
      }
    },
    "140": {
      "app": "LineMonitoring",
      "class": "line_monitoring",
      "method": "new_log",
      "data": {
        "Sensor_id": 1,
        "AbsTime": 1000,
        "counter": 1,
        "Tile_Kind": 1,
        "Motor_Speed": 100,
        "start_time": "21-10-11 23:00:43"
      }
    },
    "141": {
      "app": "LineMonitoring",
      "class": "line_monitoring",
      "method": "new_log",
      "data": {
        "Sensor_id": 1,
        "AbsTime": 1000,
        "counter": 1,
        "Tile_Kind": 1,
        "Motor_Speed": 100,
        "start_time": "21-10-11 23:00:43"
      }
    },
    "142": {
      "app": "LineMonitoring",
      "class": "line_monitoring",
      "method": "new_log",
      "data": {
        "Sensor_id": 1,
        "AbsTime": 1000,
        "counter": 1,
        "Tile_Kind": 1,
        "Motor_Speed": 100,
        "start_time": "21-10-11 23:00:43"
      }
    },
    "143": {
      "app": "LineMonitoring",
      "class": "line_monitoring",
      "method": "new_log",
      "data": {
        "Sensor_id": 1,
        "AbsTime": 1000,
        "counter": 1,
        "Tile_Kind": 1,
        "Motor_Speed": 100,
        "start_time": "21-10-11 23:00:44"
      }
    },
    "144": {
      "app": "LineMonitoring",
      "class": "line_monitoring",
      "method": "new_log",
      "data": {
        "Sensor_id": 1,
        "AbsTime": 1000,
        "counter": 1,
        "Tile_Kind": 1,
        "Motor_Speed": 100,
        "start_time": "21-10-11 23:00:44"
      }
    },
    "145": {
      "app": "LineMonitoring",
      "class": "line_monitoring",
      "method": "new_log",
      "data": {
        "Sensor_id": 1,
        "AbsTime": 1000,
        "counter": 1,
        "Tile_Kind": 1,
        "Motor_Speed": 100,
        "start_time": "21-10-11 23:00:44"
      }
    },
    "146": {
      "app": "LineMonitoring",
      "class": "line_monitoring",
      "method": "new_log",
      "data": {
        "Sensor_id": 1,
        "AbsTime": 1000,
        "counter": 1,
        "Tile_Kind": 1,
        "Motor_Speed": 100,
        "start_time": "21-10-11 23:00:44"
      }
    },
    "147": {
      "app": "LineMonitoring",
      "class": "line_monitoring",
      "method": "new_log",
      "data": {
        "Sensor_id": 1,
        "AbsTime": 1000,
        "counter": 1,
        "Tile_Kind": 1,
        "Motor_Speed": 100,
        "start_time": "21-10-11 23:00:44"
      }
    },
    "148": {
      "app": "LineMonitoring",
      "class": "line_monitoring",
      "method": "new_log",
      "data": {
        "Sensor_id": 1,
        "AbsTime": 1000,
        "counter": 1,
        "Tile_Kind": 1,
        "Motor_Speed": 100,
        "start_time": "21-10-11 23:00:44"
      }
    },
    "149": {
      "app": "LineMonitoring",
      "class": "line_monitoring",
      "method": "new_log",
      "data": {
        "Sensor_id": 1,
        "AbsTime": 1000,
        "counter": 1,
        "Tile_Kind": 1,
        "Motor_Speed": 100,
        "start_time": "21-10-11 23:00:44"
      }
    },
    "150": {
      "app": "LineMonitoring",
      "class": "line_monitoring",
      "method": "new_log",
      "data": {
        "Sensor_id": 1,
        "AbsTime": 1000,
        "counter": 1,
        "Tile_Kind": 1,
        "Motor_Speed": 100,
        "start_time": "21-10-11 23:00:44"
      }
    },
    "151": {
      "app": "LineMonitoring",
      "class": "line_monitoring",
      "method": "new_log",
      "data": {
        "Sensor_id": 1,
        "AbsTime": 1000,
        "counter": 1,
        "Tile_Kind": 1,
        "Motor_Speed": 100,
        "start_time": "21-10-11 23:00:44"
      }
    },
    "152": {
      "app": "LineMonitoring",
      "class": "line_monitoring",
      "method": "new_log",
      "data": {
        "Sensor_id": 1,
        "AbsTime": 1000,
        "counter": 1,
        "Tile_Kind": 1,
        "Motor_Speed": 100,
        "start_time": "21-10-11 23:00:44"
      }
    },
    "153": {
      "app": "LineMonitoring",
      "class": "line_monitoring",
      "method": "new_log",
      "data": {
        "Sensor_id": 1,
        "AbsTime": 1000,
        "counter": 1,
        "Tile_Kind": 1,
        "Motor_Speed": 100,
        "start_time": "21-10-11 23:00:44"
      }
    },
    "154": {
      "app": "LineMonitoring",
      "class": "line_monitoring",
      "method": "new_log",
      "data": {
        "Sensor_id": 1,
        "AbsTime": 1000,
        "counter": 1,
        "Tile_Kind": 1,
        "Motor_Speed": 100,
        "start_time": "21-10-11 23:00:44"
      }
    },
    "155": {
      "app": "LineMonitoring",
      "class": "line_monitoring",
      "method": "new_log",
      "data": {
        "Sensor_id": 1,
        "AbsTime": 1000,
        "counter": 1,
        "Tile_Kind": 1,
        "Motor_Speed": 100,
        "start_time": "21-10-11 23:00:44"
      }
    },
    "156": {
      "app": "LineMonitoring",
      "class": "line_monitoring",
      "method": "new_log",
      "data": {
        "Sensor_id": 1,
        "AbsTime": 1000,
        "counter": 1,
        "Tile_Kind": 1,
        "Motor_Speed": 100,
        "start_time": "21-10-11 23:00:44"
      }
    },
    "157": {
      "app": "LineMonitoring",
      "class": "line_monitoring",
      "method": "new_log",
      "data": {
        "Sensor_id": 1,
        "AbsTime": 1000,
        "counter": 1,
        "Tile_Kind": 1,
        "Motor_Speed": 100,
        "start_time": "21-10-11 23:00:44"
      }
    },
    "158": {
      "app": "LineMonitoring",
      "class": "line_monitoring",
      "method": "new_log",
      "data": {
        "Sensor_id": 1,
        "AbsTime": 1000,
        "counter": 1,
        "Tile_Kind": 1,
        "Motor_Speed": 100,
        "start_time": "21-10-11 23:00:44"
      }
    },
    "159": {
      "app": "LineMonitoring",
      "class": "line_monitoring",
      "method": "new_log",
      "data": {
        "Sensor_id": 1,
        "AbsTime": 1000,
        "counter": 1,
        "Tile_Kind": 1,
        "Motor_Speed": 100,
        "start_time": "21-10-11 23:00:44"
      }
    },
    "160": {
      "app": "LineMonitoring",
      "class": "line_monitoring",
      "method": "new_log",
      "data": {
        "Sensor_id": 1,
        "AbsTime": 1000,
        "counter": 1,
        "Tile_Kind": 1,
        "Motor_Speed": 100,
        "start_time": "21-10-11 23:00:44"
      }
    },
    "161": {
      "app": "LineMonitoring",
      "class": "line_monitoring",
      "method": "new_log",
      "data": {
        "Sensor_id": 1,
        "AbsTime": 1000,
        "counter": 1,
        "Tile_Kind": 1,
        "Motor_Speed": 100,
        "start_time": "21-10-11 23:00:44"
      }
    },
    "162": {
      "app": "LineMonitoring",
      "class": "line_monitoring",
      "method": "new_log",
      "data": {
        "Sensor_id": 1,
        "AbsTime": 1000,
        "counter": 1,
        "Tile_Kind": 1,
        "Motor_Speed": 100,
        "start_time": "21-10-11 23:00:44"
      }
    },
    "163": {
      "app": "LineMonitoring",
      "class": "line_monitoring",
      "method": "new_log",
      "data": {
        "Sensor_id": 1,
        "AbsTime": 1000,
        "counter": 1,
        "Tile_Kind": 1,
        "Motor_Speed": 100,
        "start_time": "21-10-11 23:00:44"
      }
    }
  }
}