{"Main": {"1": {"location": "Main", "result": "Main Start", "Time": "21-10-04 09:46:38"}, "2": {"location": "Main", "result": "Main Start", "Time": "21-10-04 09:48:22"}, "3": {"location": "Main", "result": "Main Start", "Time": "21-10-04 09:48:43"}, "4": {"location": "Backup Thread", "result": "Thread is run", "Time": "21-10-04 09:48:49"}, "5": {"location": "Login", "result": "DEVELOPER ACCESS", "Time": "21-10-04 09:48:59"}, "6": {"location": "Main Backup Thread", "result": "Stop", "Time": "21-10-04 09:49:11"}, "7": {"location": "Main", "result": "Main Start", "Time": "21-10-04 09:49:43"}, "8": {"location": "Backup Thread", "result": "Thread is run", "Time": "21-10-04 09:49:48"}, "9": {"location": "Login", "result": "DEVELOPER ACCESS", "Time": "21-10-04 09:49:52"}, "10": {"location": "Main Backup Thread", "result": "Stop", "Time": "21-10-04 09:50:20"}, "11": {"location": "Main", "result": "Main Start", "Time": "21-10-04 09:51:52"}, "12": {"location": "Backup Thread", "result": "Thread is run", "Time": "21-10-04 09:51:57"}, "13": {"location": "Main", "result": "Main Start", "Time": "21-10-04 09:59:21"}, "14": {"location": "Backup Thread", "result": "Thread is run", "Time": "21-10-04 09:59:26"}, "15": {"location": "Main", "result": "Main Start", "Time": "21-10-04 10:02:25"}, "16": {"location": "Backup Thread", "result": "Thread is run", "Time": "21-10-04 10:02:30"}, "17": {"location": "Login", "result": "DEVELOPER ACCESS", "Time": "21-10-04 10:02:36"}, "18": {"location": "Login", "result": "DEVELOPER ACCESS", "Time": "21-10-04 10:02:46"}, "19": {"location": "Main", "result": "Main Start", "Time": "21-10-04 10:04:02"}, "20": {"location": "Backup Thread", "result": "Thread is run", "Time": "21-10-04 10:04:06"}, "21": {"location": "Login", "result": "DEVELOPER ACCESS", "Time": "21-10-04 10:04:12"}, "22": {"location": "Login", "result": "DEVELOPER ACCESS", "Time": "21-10-04 10:04:19"}, "23": {"location": "Main Backup Thread", "result": "Stop", "Time": "21-10-04 10:04:28"}, "24": {"location": "Main", "result": "Main Start", "Time": "21-10-04 10:11:21"}, "25": {"location": "Backup Thread", "result": "Thread is run", "Time": "21-10-04 10:11:26"}, "26": {"location": "Login", "result": "DEVELOPER ACCESS", "Time": "21-10-04 10:11:29"}, "27": {"location": "Login", "result": "DEVELOPER ACCESS", "Time": "21-10-04 10:11:33"}, "28": {"location": "Login", "result": "DEVELOPER ACCESS", "Time": "21-10-04 10:11:36"}, "29": {"location": "Main Backup Thread", "result": "Stop", "Time": "21-10-04 10:11:47"}, "30": {"location": "Main", "result": "Main Start", "Time": "21-10-04 10:12:17"}, "31": {"location": "Backup Thread", "result": "Thread is run", "Time": "21-10-04 10:12:22"}, "32": {"location": "Login", "result": "DEVELOPER ACCESS", "Time": "21-10-04 10:12:24"}, "33": {"location": "Login", "result": "DEVELOPER ACCESS", "Time": "21-10-04 10:12:27"}, "34": {"location": "Main Backup Thread", "result": "Stop", "Time": "21-10-04 10:12:53"}, "35": {"location": "Main", "result": "Main Start", "Time": "21-10-04 10:14:38"}, "36": {"location": "Backup Thread", "result": "Thread is run", "Time": "21-10-04 10:14:43"}, "37": {"location": "Login", "result": "DEVELOPER ACCESS", "Time": "21-10-04 10:14:46"}, "38": {"location": "Main Backup Thread", "result": "Stop", "Time": "21-10-04 10:15:04"}, "39": {"location": "Main", "result": "Main Start", "Time": "21-10-04 10:16:01"}, "40": {"location": "Backup Thread", "result": "Thread is run", "Time": "21-10-04 10:16:05"}, "41": {"location": "Login", "result": "DEVELOPER ACCESS", "Time": "21-10-04 10:16:08"}, "42": {"location": "Login", "result": "DEVELOPER ACCESS", "Time": "21-10-04 10:16:28"}, "43": {"location": "Main Backup Thread", "result": "Stop", "Time": "21-10-04 10:16:47"}, "44": {"location": "Main", "result": "Main Start", "Time": "21-10-04 10:16:55"}, "45": {"location": "Backup Thread", "result": "Thread is run", "Time": "21-10-04 10:16:59"}, "46": {"location": "Login", "result": "DEVELOPER ACCESS", "Time": "21-10-04 10:17:08"}, "47": {"location": "Main Backup Thread", "result": "Stop", "Time": "21-10-04 10:17:31"}, "48": {"location": "Login", "result": "DEVELOPER ACCESS", "Time": "21-10-09 16:52:54"}, "49": {"location": "Login", "result": "DEVELOPER ACCESS", "Time": "21-10-09 17:09:29"}, "50": {"location": "Login", "result": "DEVELOPER ACCESS", "Time": "21-10-09 17:13:48"}, "51": {"location": "Login", "result": "DEVELOPER ACCESS", "Time": "21-10-09 17:15:49"}, "52": {"location": "Login", "result": "DEVELOPER ACCESS", "Time": "21-10-09 17:19:01"}, "53": {"location": "Main Backup Thread", "result": "Stop", "Time": "21-10-09 17:19:22"}, "54": {"location": "Login", "result": "DEVELOPER ACCESS", "Time": "21-10-09 17:25:11"}, "55": {"location": "Main Backup Thread", "result": "Stop", "Time": "21-10-09 17:25:24"}, "56": {"location": "Login", "result": "DEVELOPER ACCESS", "Time": "21-10-10 16:11:32"}, "57": {"location": "Main Backup Thread", "result": "Stop", "Time": "21-10-10 16:11:40"}, "58": {"location": "Login", "result": "DEVELOPER ACCESS", "Time": "21-10-10 17:44:25"}, "59": {"location": "Login", "result": "DEVELOPER ACCESS", "Time": "21-10-10 17:45:25"}, "60": {"location": "Main Backup Thread", "result": "Stop", "Time": "21-10-10 17:45:45"}, "61": {"location": "Login", "result": "DEVELOPER ACCESS", "Time": "21-10-10 17:46:57"}, "62": {"location": "Login", "result": "DEVELOPER ACCESS", "Time": "21-10-10 17:47:54"}, "63": {"location": "Login", "result": "DEVELOPER ACCESS", "Time": "21-10-10 17:47:58"}, "64": {"location": "Main Backup Thread", "result": "Stop", "Time": "21-10-10 17:48:13"}, "65": {"location": "Login", "result": "DEVELOPER ACCESS", "Time": "21-10-10 17:49:30"}, "66": {"location": "Main Backup Thread", "result": "Stop", "Time": "21-10-10 17:49:40"}, "67": {"location": "Login", "result": "DEVELOPER ACCESS", "Time": "21-10-10 18:13:30"}, "68": {"location": "Login", "result": "DEVELOPER ACCESS", "Time": "21-10-10 18:16:24"}, "69": {"location": "Main Backup Thread", "result": "Stop", "Time": "21-10-10 18:16:44"}, "70": {"location": "Login", "result": "DEVELOPER ACCESS", "Time": "21-10-10 18:16:59"}, "71": {"location": "Main Backup Thread", "result": "Stop", "Time": "21-10-10 18:17:15"}, "72": {"location": "Login", "result": "DEVELOPER ACCESS", "Time": "21-10-11 15:45:02"}, "73": {"location": "Login", "result": "DEVELOPER ACCESS", "Time": "21-10-11 15:45:12"}, "74": {"location": "Main Backup Thread", "result": "Stop", "Time": "21-10-11 15:45:33"}, "75": {"location": "Login", "result": "DEVELOPER ACCESS", "Time": "21-10-11 15:51:26"}, "76": {"location": "Login", "result": "DEVELOPER ACCESS", "Time": "21-10-11 15:51:37"}, "77": {"location": "Main Backup Thread", "result": "Stop", "Time": "21-10-11 15:51:58"}, "78": {"location": "Login", "result": "DEVELOPER ACCESS", "Time": "21-10-11 16:00:45"}, "79": {"location": "Main Backup Thread", "result": "Stop", "Time": "21-10-11 16:01:06"}, "80": {"location": "Login", "result": "DEVELOPER ACCESS", "Time": "21-10-11 16:19:46"}, "81": {"location": "Main Backup Thread", "result": "Stop", "Time": "21-10-11 16:20:10"}}, "LineMonitoring": {"1": {"location": "get api/phones", "result": "OOps: Something Else", "Time": "21-10-04 09:46:48"}, "2": {"location": "get api/phones", "result": "OOps: Something Else", "Time": "21-10-04 09:46:48"}, "3": {"location": "get api/phones", "result": "OOps: Something Else", "Time": "21-10-04 09:48:24"}, "4": {"location": "get api/phones", "result": "OOps: Something Else", "Time": "21-10-04 09:48:24"}, "5": {"location": "get api/phones", "result": "OOps: Something Else", "Time": "21-10-04 09:48:45"}, "6": {"location": "get api/phones", "result": "OOps: Something Else", "Time": "21-10-04 09:48:45"}, "7": {"location": "Init Render", "result": "Start", "Time": "21-10-04 09:48:47"}, "8": {"location": "get http://localhost/Hafez/Monitoring_Tile/api/da_unit", "result": "\u0645\u0634\u06a9\u0644 \u062f\u06cc\u06af\u0647 \u062f\u0631 \u0633\u06cc\u0633\u062a\u0645 \u0627\u0633\u062a", "Time": "21-10-04 09:48:49"}, "9": {"location": "Main Rendering Thread", "result": "Stop", "Time": "21-10-04 09:49:12"}, "10": {"location": "Main Rendering Thread", "result": "Stop", "Time": "21-10-04 09:49:12"}, "11": {"location": "get api/phones", "result": "OOps: Something Else", "Time": "21-10-04 09:49:45"}, "12": {"location": "get api/phones", "result": "OOps: Something Else", "Time": "21-10-04 09:49:45"}, "13": {"location": "Init Render", "result": "Start", "Time": "21-10-04 09:49:47"}, "14": {"location": "get http://localhost/Hafez/Monitoring_Tile/api/da_unit", "result": "\u0645\u0634\u06a9\u0644 \u062f\u06cc\u06af\u0647 \u062f\u0631 \u0633\u06cc\u0633\u062a\u0645 \u0627\u0633\u062a", "Time": "21-10-04 09:49:48"}, "15": {"location": "Main Rendering Thread", "result": "Stop", "Time": "21-10-04 09:50:22"}, "16": {"location": "Main Rendering Thread", "result": "Stop", "Time": "21-10-04 09:50:22"}, "17": {"location": "get api/phones", "result": "OOps: Something Else", "Time": "21-10-04 09:51:54"}, "18": {"location": "get api/phones", "result": "OOps: Something Else", "Time": "21-10-04 09:51:54"}, "19": {"location": "Init Render", "result": "Start", "Time": "21-10-04 09:51:56"}, "20": {"location": "get http://localhost/Hafez/Monitoring_Tile/api/da_unit", "result": "\u0645\u0634\u06a9\u0644 \u062f\u06cc\u06af\u0647 \u062f\u0631 \u0633\u06cc\u0633\u062a\u0645 \u0627\u0633\u062a", "Time": "21-10-04 09:51:57"}, "21": {"location": "get api/phones", "result": "OOps: Something Else", "Time": "21-10-04 09:59:23"}, "22": {"location": "get api/phones", "result": "OOps: Something Else", "Time": "21-10-04 09:59:23"}, "23": {"location": "Init Render", "result": "Start", "Time": "21-10-04 09:59:25"}, "24": {"location": "get http://localhost/Hafez/Monitoring_Tile/api/da_unit", "result": "\u0645\u0634\u06a9\u0644 \u062f\u06cc\u06af\u0647 \u062f\u0631 \u0633\u06cc\u0633\u062a\u0645 \u0627\u0633\u062a", "Time": "21-10-04 09:59:26"}, "25": {"location": "get api/phones", "result": "OOps: Something Else", "Time": "21-10-04 10:02:27"}, "26": {"location": "get api/phones", "result": "OOps: Something Else", "Time": "21-10-04 10:02:27"}, "27": {"location": "Init Render", "result": "Start", "Time": "21-10-04 10:02:29"}, "28": {"location": "get http://localhost/Hafez/Monitoring_Tile/api/da_unit", "result": "\u0645\u0634\u06a9\u0644 \u062f\u06cc\u06af\u0647 \u062f\u0631 \u0633\u06cc\u0633\u062a\u0645 \u0627\u0633\u062a", "Time": "21-10-04 10:02:30"}, "29": {"location": "Main Rendering Thread", "result": "Stop", "Time": "21-10-04 10:02:54"}, "30": {"location": "Main Rendering Thread", "result": "Stop", "Time": "21-10-04 10:02:54"}, "31": {"location": "Restart Render", "result": "Start", "Time": "21-10-04 10:02:54"}, "32": {"location": "Main Rendering Thread", "result": "Stop", "Time": "21-10-04 10:02:59"}, "33": {"location": "Main Rendering Thread", "result": "Stop", "Time": "21-10-04 10:02:59"}, "34": {"location": "get api/phones", "result": "OOps: Something Else", "Time": "21-10-04 10:04:03"}, "35": {"location": "get api/phones", "result": "OOps: Something Else", "Time": "21-10-04 10:04:03"}, "36": {"location": "Init Render", "result": "Start", "Time": "21-10-04 10:04:05"}, "37": {"location": "get http://localhost/Hafez/Monitoring_Tile/api/da_unit", "result": "\u0645\u0634\u06a9\u0644 \u062f\u06cc\u06af\u0647 \u062f\u0631 \u0633\u06cc\u0633\u062a\u0645 \u0627\u0633\u062a", "Time": "21-10-04 10:04:06"}, "38": {"location": "Main Rendering Thread", "result": "Stop", "Time": "21-10-04 10:04:30"}, "39": {"location": "Main Rendering Thread", "result": "Stop", "Time": "21-10-04 10:04:30"}, "40": {"location": "get api/phones", "result": "OOps: Something Else", "Time": "21-10-04 10:11:22"}, "41": {"location": "get api/phones", "result": "OOps: Something Else", "Time": "21-10-04 10:11:22"}, "42": {"location": "Init Render", "result": "Start", "Time": "21-10-04 10:11:25"}, "43": {"location": "get http://localhost/Hafez/Monitoring_Tile/api/da_unit", "result": "\u0645\u0634\u06a9\u0644 \u062f\u06cc\u06af\u0647 \u062f\u0631 \u0633\u06cc\u0633\u062a\u0645 \u0627\u0633\u062a", "Time": "21-10-04 10:11:25"}, "44": {"location": "Main Rendering Thread", "result": "Stop", "Time": "21-10-04 10:11:50"}, "45": {"location": "Main Rendering Thread", "result": "Stop", "Time": "21-10-04 10:11:50"}, "46": {"location": "get api/phones", "result": "OOps: Something Else", "Time": "21-10-04 10:12:18"}, "47": {"location": "get api/phones", "result": "OOps: Something Else", "Time": "21-10-04 10:12:18"}, "48": {"location": "Init Render", "result": "Start", "Time": "21-10-04 10:12:21"}, "49": {"location": "get http://localhost/Hafez/Monitoring_Tile/api/da_unit", "result": "\u0645\u0634\u06a9\u0644 \u062f\u06cc\u06af\u0647 \u062f\u0631 \u0633\u06cc\u0633\u062a\u0645 \u0627\u0633\u062a", "Time": "21-10-04 10:12:21"}, "50": {"location": "Main Rendering Thread", "result": "Stop", "Time": "21-10-04 10:12:56"}, "51": {"location": "Main Rendering Thread", "result": "Stop", "Time": "21-10-04 10:12:56"}, "52": {"location": "get api/phones", "result": "OOps: Something Else", "Time": "21-10-04 10:14:39"}, "53": {"location": "get api/phones", "result": "OOps: Something Else", "Time": "21-10-04 10:14:39"}, "54": {"location": "Init Render", "result": "Start", "Time": "21-10-04 10:14:42"}, "55": {"location": "get http://localhost/Hafez/Monitoring_Tile/api/da_unit", "result": "\u0645\u0634\u06a9\u0644 \u062f\u06cc\u06af\u0647 \u062f\u0631 \u0633\u06cc\u0633\u062a\u0645 \u0627\u0633\u062a", "Time": "21-10-04 10:14:42"}, "56": {"location": "Main Rendering Thread", "result": "Stop", "Time": "21-10-04 10:15:07"}, "57": {"location": "Main Rendering Thread", "result": "Stop", "Time": "21-10-04 10:15:07"}, "58": {"location": "get api/phones", "result": "OOps: Something Else", "Time": "21-10-04 10:16:02"}, "59": {"location": "get api/phones", "result": "OOps: Something Else", "Time": "21-10-04 10:16:02"}, "60": {"location": "Init Render", "result": "Start", "Time": "21-10-04 10:16:05"}, "61": {"location": "get http://localhost/Hafez/Monitoring_Tile/api/da_unit", "result": "\u0645\u0634\u06a9\u0644 \u062f\u06cc\u06af\u0647 \u062f\u0631 \u0633\u06cc\u0633\u062a\u0645 \u0627\u0633\u062a", "Time": "21-10-04 10:16:05"}, "62": {"location": "Main Rendering Thread", "result": "Stop", "Time": "21-10-04 10:16:50"}, "63": {"location": "Main Rendering Thread", "result": "Stop", "Time": "21-10-04 10:16:50"}, "64": {"location": "get api/phones", "result": "OOps: Something Else", "Time": "21-10-04 10:16:56"}, "65": {"location": "get api/phones", "result": "OOps: Something Else", "Time": "21-10-04 10:16:56"}, "66": {"location": "Init Render", "result": "Start", "Time": "21-10-04 10:16:58"}, "67": {"location": "get http://localhost/Hafez/Monitoring_Tile/api/da_unit", "result": "\u0645\u0634\u06a9\u0644 \u062f\u06cc\u06af\u0647 \u062f\u0631 \u0633\u06cc\u0633\u062a\u0645 \u0627\u0633\u062a", "Time": "21-10-04 10:16:59"}, "68": {"location": "Main Rendering Thread", "result": "Stop", "Time": "21-10-04 10:17:34"}, "69": {"location": "Main Rendering Thread", "result": "Stop", "Time": "21-10-04 10:17:34"}, "70": {"location": "Init Render", "result": "Start", "Time": "21-10-09 16:48:10"}, "71": {"location": "Init Render", "result": "Start", "Time": "21-10-09 16:49:15"}, "72": {"location": "Init Render", "result": "Start", "Time": "21-10-09 16:50:38"}, "73": {"location": "Init Render", "result": "Start", "Time": "21-10-09 16:52:02"}, "74": {"location": "Init Render", "result": "Start", "Time": "21-10-09 17:09:23"}, "75": {"location": "Init Render", "result": "Start", "Time": "21-10-09 17:10:37"}, "76": {"location": "Init Render", "result": "Start", "Time": "21-10-09 17:11:22"}, "77": {"location": "Init Render", "result": "Start", "Time": "21-10-09 17:13:11"}, "78": {"location": "Init Render", "result": "Start", "Time": "21-10-09 17:13:44"}, "79": {"location": "Init Render", "result": "Start", "Time": "21-10-09 17:15:36"}, "80": {"location": "Init Render", "result": "Start", "Time": "21-10-09 17:17:14"}, "81": {"location": "Init Render", "result": "Start", "Time": "21-10-09 17:18:00"}, "82": {"location": "Main Rendering Thread", "result": "Stop", "Time": "21-10-09 17:19:25"}, "83": {"location": "Main Rendering Thread", "result": "Stop", "Time": "21-10-09 17:19:25"}, "84": {"location": "Init Render", "result": "Start", "Time": "21-10-09 17:21:07"}, "85": {"location": "Init Render", "result": "Start", "Time": "21-10-09 17:23:06"}, "86": {"location": "Init Render", "result": "Start", "Time": "21-10-09 17:23:22"}, "87": {"location": "Main Rendering Thread", "result": "Stop", "Time": "21-10-09 17:25:25"}, "88": {"location": "Main Rendering Thread", "result": "Stop", "Time": "21-10-09 17:25:25"}, "89": {"location": "Init Render", "result": "Start", "Time": "21-10-10 16:09:58"}, "90": {"location": "get http://localhost/Hafez/Monitoring_Tile/api/get/Check", "result": "\u0645\u0634\u06a9\u0644 \u062f\u06cc\u06af\u0647 \u062f\u0631 \u0633\u06cc\u0633\u062a\u0645 \u0627\u0633\u062a", "Time": "21-10-10 16:10:02"}, "91": {"location": "Main Rendering Thread", "result": "Stop", "Time": "21-10-10 16:11:41"}, "92": {"location": "Main Rendering Thread", "result": "Stop", "Time": "21-10-10 16:11:41"}, "93": {"location": "Init Render", "result": "Start", "Time": "21-10-10 17:44:02"}, "94": {"location": "get http://localhost/Hafez/Monitoring_Tile/api/get/Check", "result": "\u0645\u0634\u06a9\u0644 \u062f\u06cc\u06af\u0647 \u062f\u0631 \u0633\u06cc\u0633\u062a\u0645 \u0627\u0633\u062a", "Time": "21-10-10 17:44:05"}, "95": {"location": "get http://localhost/Hafez/Monitoring_Tile/api/get/Check", "result": "\u0645\u0634\u06a9\u0644 \u062f\u06cc\u06af\u0647 \u062f\u0631 \u0633\u06cc\u0633\u062a\u0645 \u0627\u0633\u062a", "Time": "21-10-10 17:44:05"}, "96": {"location": "get http://localhost/Hafez/Monitoring_Tile/api/get/Check", "result": "\u0645\u0634\u06a9\u0644 \u062f\u06cc\u06af\u0647 \u062f\u0631 \u0633\u06cc\u0633\u062a\u0645 \u0627\u0633\u062a", "Time": "21-10-10 17:45:22"}, "97": {"location": "get http://localhost/Hafez/Monitoring_Tile/api/get/Check", "result": "\u0645\u0634\u06a9\u0644 \u062f\u06cc\u06af\u0647 \u062f\u0631 \u0633\u06cc\u0633\u062a\u0645 \u0627\u0633\u062a", "Time": "21-10-10 17:45:22"}, "98": {"location": "Main Rendering Thread", "result": "Stop", "Time": "21-10-10 17:45:45"}, "99": {"location": "Main Rendering Thread", "result": "Stop", "Time": "21-10-10 17:45:45"}, "100": {"location": "Init Render", "result": "Start", "Time": "21-10-10 17:46:49"}, "101": {"location": "get http://localhost/Hafez/Monitoring_Tile/api/get/Check", "result": "\u0645\u0634\u06a9\u0644 \u062f\u06cc\u06af\u0647 \u062f\u0631 \u0633\u06cc\u0633\u062a\u0645 \u0627\u0633\u062a", "Time": "21-10-10 17:46:53"}, "102": {"location": "get http://localhost/Hafez/Monitoring_Tile/api/get/Check", "result": "\u0645\u0634\u06a9\u0644 \u062f\u06cc\u06af\u0647 \u062f\u0631 \u0633\u06cc\u0633\u062a\u0645 \u0627\u0633\u062a", "Time": "21-10-10 17:46:53"}, "103": {"location": "get http://localhost/Hafez/Monitoring_Tile/api/get/Check", "result": "\u0645\u0634\u06a9\u0644 \u062f\u06cc\u06af\u0647 \u062f\u0631 \u0633\u06cc\u0633\u062a\u0645 \u0627\u0633\u062a", "Time": "21-10-10 17:47:02"}, "104": {"location": "get http://localhost/Hafez/Monitoring_Tile/api/get/Check", "result": "\u0645\u0634\u06a9\u0644 \u062f\u06cc\u06af\u0647 \u062f\u0631 \u0633\u06cc\u0633\u062a\u0645 \u0627\u0633\u062a", "Time": "21-10-10 17:47:02"}, "105": {"location": "Init Render", "result": "Start", "Time": "21-10-10 17:47:50"}, "106": {"location": "get http://localhost/Hafez/Monitoring_Tile/api/get/Check", "result": "\u0645\u0634\u06a9\u0644 \u062f\u06cc\u06af\u0647 \u062f\u0631 \u0633\u06cc\u0633\u062a\u0645 \u0627\u0633\u062a", "Time": "21-10-10 17:47:54"}, "107": {"location": "get http://localhost/Hafez/Monitoring_Tile/api/get/Check", "result": "\u0645\u0634\u06a9\u0644 \u062f\u06cc\u06af\u0647 \u062f\u0631 \u0633\u06cc\u0633\u062a\u0645 \u0627\u0633\u062a", "Time": "21-10-10 17:47:54"}, "108": {"location": "Main Rendering Thread", "result": "Stop", "Time": "21-10-10 17:48:14"}, "109": {"location": "Main Rendering Thread", "result": "Stop", "Time": "21-10-10 17:48:14"}, "110": {"location": "Init Render", "result": "Start", "Time": "21-10-10 17:49:18"}, "111": {"location": "get http://localhost/Hafez/Monitoring_Tile/api/get/Check", "result": "\u0645\u0634\u06a9\u0644 \u062f\u06cc\u06af\u0647 \u062f\u0631 \u0633\u06cc\u0633\u062a\u0645 \u0627\u0633\u062a", "Time": "21-10-10 17:49:21"}, "112": {"location": "Main Rendering Thread", "result": "Stop", "Time": "21-10-10 17:49:41"}, "113": {"location": "Main Rendering Thread", "result": "Stop", "Time": "21-10-10 17:49:41"}, "114": {"location": "Init Render", "result": "Start", "Time": "21-10-10 18:13:22"}, "115": {"location": "Main Rendering Thread", "result": "Stop", "Time": "21-10-10 18:16:44"}, "116": {"location": "Main Rendering Thread", "result": "Stop", "Time": "21-10-10 18:16:44"}, "117": {"location": "Init Render", "result": "Start", "Time": "21-10-10 18:16:53"}, "118": {"location": "Main Rendering Thread", "result": "Stop", "Time": "21-10-10 18:17:16"}, "119": {"location": "Main Rendering Thread", "result": "Stop", "Time": "21-10-10 18:17:16"}, "120": {"location": "Init Render", "result": "Start", "Time": "21-10-10 18:18:28"}, "121": {"location": "Init Render", "result": "Start", "Time": "21-10-10 18:18:49"}, "122": {"location": "Init Render", "result": "Start", "Time": "21-10-11 15:44:18"}, "123": {"location": "Init Render", "result": "Start", "Time": "21-10-11 15:44:50"}, "124": {"location": "Main Rendering Thread", "result": "Stop", "Time": "21-10-11 15:45:34"}, "125": {"location": "Main Rendering Thread", "result": "Stop", "Time": "21-10-11 15:45:34"}, "126": {"location": "Init Render", "result": "Start", "Time": "21-10-11 15:51:15"}, "127": {"location": "Main Rendering Thread", "result": "Stop", "Time": "21-10-11 15:51:58"}, "128": {"location": "Main Rendering Thread", "result": "Stop", "Time": "21-10-11 15:51:58"}, "129": {"location": "Init Render", "result": "Start", "Time": "21-10-11 15:55:23"}, "130": {"location": "Check Choose", "result": "Sensor not Found , Choose : 245", "Time": "21-10-11 15:55:32"}, "131": {"location": "Check Choose", "result": "Sensor not Found , Choose : 245", "Time": "21-10-11 15:55:38"}, "132": {"location": "Check Choose", "result": "Sensor not Found , Choose : 245", "Time": "21-10-11 15:55:44"}, "133": {"location": "Check Choose", "result": "Sensor not Found , Choose : 245", "Time": "21-10-11 15:55:50"}, "134": {"location": "Check Choose", "result": "Sensor not Found , Choose : 245", "Time": "21-10-11 15:55:56"}, "135": {"location": "Check Choose", "result": "Sensor not Found , Choose : 245", "Time": "21-10-11 15:56:03"}, "136": {"location": "Check Choose", "result": "Sensor not Found , Choose : 245", "Time": "21-10-11 15:56:09"}, "137": {"location": "Check Choose", "result": "Sensor not Found , Choose : 245", "Time": "21-10-11 15:56:15"}, "138": {"location": "Check Choose", "result": "Sensor not Found , Choose : 245", "Time": "21-10-11 15:56:21"}, "139": {"location": "Check Choose", "result": "Sensor not Found , Choose : 245", "Time": "21-10-11 15:56:27"}, "140": {"location": "Check Choose", "result": "Sensor not Found , Choose : 245", "Time": "21-10-11 15:56:33"}, "141": {"location": "Check Choose", "result": "Sensor not Found , Choose : 245", "Time": "21-10-11 15:56:39"}, "142": {"location": "Check Choose", "result": "Sensor not Found , Choose : 245", "Time": "21-10-11 15:56:45"}, "143": {"location": "Check Choose", "result": "Sensor not Found , Choose : 245", "Time": "21-10-11 15:56:51"}, "144": {"location": "Check Choose", "result": "Sensor not Found , Choose : 245", "Time": "21-10-11 15:56:57"}, "145": {"location": "Check Choose", "result": "Sensor not Found , Choose : 245", "Time": "21-10-11 15:57:03"}, "146": {"location": "Check Choose", "result": "Sensor not Found , Choose : 245", "Time": "21-10-11 15:57:09"}, "147": {"location": "Check Choose", "result": "Sensor not Found , Choose : 245", "Time": "21-10-11 15:57:15"}, "148": {"location": "Check Choose", "result": "Sensor not Found , Choose : 245", "Time": "21-10-11 15:57:21"}, "149": {"location": "Check Choose", "result": "Sensor not Found , Choose : 245", "Time": "21-10-11 15:57:27"}, "150": {"location": "Check Choose", "result": "Sensor not Found , Choose : 245", "Time": "21-10-11 15:57:34"}, "151": {"location": "Check Choose", "result": "Sensor not Found , Choose : 245", "Time": "21-10-11 15:57:40"}, "152": {"location": "Check Choose", "result": "Sensor not Found , Choose : 245", "Time": "21-10-11 15:57:46"}, "153": {"location": "Check Choose", "result": "Sensor not Found , Choose : 245", "Time": "21-10-11 15:57:52"}, "154": {"location": "Check Choose", "result": "Sensor not Found , Choose : 245", "Time": "21-10-11 15:57:58"}, "155": {"location": "Check Choose", "result": "Sensor not Found , Choose : 245", "Time": "21-10-11 15:58:04"}, "156": {"location": "Check Choose", "result": "Sensor not Found , Choose : 245", "Time": "21-10-11 15:58:10"}, "157": {"location": "Check Choose", "result": "Sensor not Found , Choose : 245", "Time": "21-10-11 15:58:16"}, "158": {"location": "Check Choose", "result": "Sensor not Found , Choose : 245", "Time": "21-10-11 15:58:22"}, "159": {"location": "Check Choose", "result": "Sensor not Found , Choose : 245", "Time": "21-10-11 15:58:28"}, "160": {"location": "Check Choose", "result": "Sensor not Found , Choose : 245", "Time": "21-10-11 15:58:34"}, "161": {"location": "Check Choose", "result": "Sensor not Found , Choose : 245", "Time": "21-10-11 15:58:40"}, "162": {"location": "Check Choose", "result": "Sensor not Found , Choose : 245", "Time": "21-10-11 15:58:46"}, "163": {"location": "Check Choose", "result": "Sensor not Found , Choose : 245", "Time": "21-10-11 15:58:52"}, "164": {"location": "Check Choose", "result": "Sensor not Found , Choose : 245", "Time": "21-10-11 15:58:58"}, "165": {"location": "Check Choose", "result": "Sensor not Found , Choose : 245", "Time": "21-10-11 15:59:04"}, "166": {"location": "Check Choose", "result": "Sensor not Found , Choose : 245", "Time": "21-10-11 15:59:10"}, "167": {"location": "Check Choose", "result": "Sensor not Found , Choose : 245", "Time": "21-10-11 15:59:16"}, "168": {"location": "Check Choose", "result": "Sensor not Found , Choose : 245", "Time": "21-10-11 15:59:22"}, "169": {"location": "Check Choose", "result": "Sensor not Found , Choose : 245", "Time": "21-10-11 15:59:54"}, "170": {"location": "Check Choose", "result": "Sensor not Found , Choose : 245", "Time": "21-10-11 16:00:00"}, "171": {"location": "Check Choose", "result": "Sensor not Found , Choose : 245", "Time": "21-10-11 16:00:07"}, "172": {"location": "Check Choose", "result": "Sensor not Found , Choose : 245", "Time": "21-10-11 16:00:26"}, "173": {"location": "Check Choose", "result": "Sensor not Found , Choose : 245", "Time": "21-10-11 16:00:33"}, "174": {"location": "Check Choose", "result": "Sensor not Found , Choose : 245", "Time": "21-10-11 16:00:39"}, "175": {"location": "Check Choose", "result": "Sensor not Found , Choose : 245", "Time": "21-10-11 16:00:45"}, "176": {"location": "Check Choose", "result": "Sensor not Found , Choose : 245", "Time": "21-10-11 16:00:51"}, "177": {"location": "Check Choose", "result": "Sensor not Found , Choose : 245", "Time": "21-10-11 16:00:57"}, "178": {"location": "Check Choose", "result": "Sensor not Found , Choose : 245", "Time": "21-10-11 16:01:03"}, "179": {"location": "Main Rendering Thread", "result": "Stop", "Time": "21-10-11 16:01:07"}, "180": {"location": "Main Rendering Thread", "result": "Stop", "Time": "21-10-11 16:01:07"}, "181": {"location": "Init Render", "result": "Start", "Time": "21-10-11 16:19:37"}, "182": {"location": "Main Rendering Thread", "result": "Stop", "Time": "21-10-11 16:20:11"}, "183": {"location": "Main Rendering Thread", "result": "Stop", "Time": "21-10-11 16:20:11"}}, "Bale": {"1": {"location": "Bale Init", "result": "OpenThread is run", "Time": "21-10-04 09:46:48"}, "2": {"location": "Bale Init", "result": "SendThread is run", "Time": "21-10-04 09:46:48"}, "3": {"location": "Main Open Thread", "result": "Connect", "Time": "21-10-04 09:46:50"}, "4": {"location": "Bale Init", "result": "OpenThread is run", "Time": "21-10-04 09:48:24"}, "5": {"location": "Bale Init", "result": "SendThread is run", "Time": "21-10-04 09:48:24"}, "6": {"location": "Main Open Thread", "result": "Connect", "Time": "21-10-04 09:48:30"}, "7": {"location": "Bale Init", "result": "OpenThread is run", "Time": "21-10-04 09:48:45"}, "8": {"location": "Bale Init", "result": "SendThread is run", "Time": "21-10-04 09:48:45"}, "9": {"location": "Main Open Thread", "result": "Connect", "Time": "21-10-04 09:48:45"}, "10": {"location": "Main Send Thread", "result": "Stop", "Time": "21-10-04 09:49:00"}, "11": {"location": "Main Open Thread", "result": "Stop", "Time": "21-10-04 09:49:05"}, "12": {"location": "Bale Init", "result": "OpenThread is run", "Time": "21-10-04 09:49:45"}, "13": {"location": "Bale Init", "result": "SendThread is run", "Time": "21-10-04 09:49:45"}, "14": {"location": "Main Open Thread", "result": "Connect", "Time": "21-10-04 09:49:51"}, "15": {"location": "Main Send Thread", "result": "Stop", "Time": "21-10-04 09:49:53"}, "16": {"location": "Main Open Thread", "result": "Stop", "Time": "21-10-04 09:50:12"}, "17": {"location": "Bale Init", "result": "OpenThread is run", "Time": "21-10-04 09:51:54"}, "18": {"location": "Bale Init", "result": "SendThread is run", "Time": "21-10-04 09:51:54"}, "19": {"location": "Main Open Thread", "result": "Connect", "Time": "21-10-04 09:51:54"}, "20": {"location": "Bale Init", "result": "OpenThread is run", "Time": "21-10-04 09:59:23"}, "21": {"location": "Bale Init", "result": "SendThread is run", "Time": "21-10-04 09:59:23"}, "22": {"location": "Main Open Thread", "result": "Connect", "Time": "21-10-04 09:59:28"}, "23": {"location": "Bale Init", "result": "OpenThread is run", "Time": "21-10-04 10:02:27"}, "24": {"location": "Bale Init", "result": "SendThread is run", "Time": "21-10-04 10:02:27"}, "25": {"location": "Main Open Thread", "result": "Connect", "Time": "21-10-04 10:02:27"}, "26": {"location": "Bale Init", "result": "OpenThread is run", "Time": "21-10-04 10:04:03"}, "27": {"location": "Bale Init", "result": "SendThread is run", "Time": "21-10-04 10:04:03"}, "28": {"location": "Main Open Thread", "result": "Connect", "Time": "21-10-04 10:04:04"}, "29": {"location": "Main Send Thread", "result": "Stop", "Time": "21-10-04 10:04:20"}, "30": {"location": "Main Open Thread", "result": "Stop", "Time": "21-10-04 10:04:24"}, "31": {"location": "Bale Init", "result": "OpenThread is run", "Time": "21-10-04 10:11:22"}, "32": {"location": "Bale Init", "result": "SendThread is run", "Time": "21-10-04 10:11:22"}, "33": {"location": "Main Open Thread", "result": "Connect", "Time": "21-10-04 10:11:24"}, "34": {"location": "Main Send Thread", "result": "Stop", "Time": "21-10-04 10:11:37"}, "35": {"location": "Main Open Thread", "result": "Stop", "Time": "21-10-04 10:11:44"}, "36": {"location": "Bale Init", "result": "OpenThread is run", "Time": "21-10-04 10:12:18"}, "37": {"location": "Bale Init", "result": "SendThread is run", "Time": "21-10-04 10:12:18"}, "38": {"location": "Main Open Thread", "result": "Connect", "Time": "21-10-04 10:12:27"}, "39": {"location": "Main Send Thread", "result": "Stop", "Time": "21-10-04 10:12:28"}, "40": {"location": "Main Open Thread", "result": "Stop", "Time": "21-10-04 10:12:47"}, "41": {"location": "Bale Init", "result": "OpenThread is run", "Time": "21-10-04 10:14:39"}, "42": {"location": "Bale Init", "result": "SendThread is run", "Time": "21-10-04 10:14:39"}, "43": {"location": "Main Open Thread", "result": "Connect", "Time": "21-10-04 10:14:40"}, "44": {"location": "Main Send Thread", "result": "Stop", "Time": "21-10-04 10:14:47"}, "45": {"location": "Main Open Thread", "result": "Stop", "Time": "21-10-04 10:15:00"}, "46": {"location": "Bale Init", "result": "OpenThread is run", "Time": "21-10-04 10:16:02"}, "47": {"location": "Bale Init", "result": "SendThread is run", "Time": "21-10-04 10:16:02"}, "48": {"location": "Main Open Thread", "result": "Connect", "Time": "21-10-04 10:16:03"}, "49": {"location": "Main Send Thread", "result": "Stop", "Time": "21-10-04 10:16:29"}, "50": {"location": "Main Open Thread", "result": "Stop", "Time": "21-10-04 10:16:43"}, "51": {"location": "Bale Init", "result": "OpenThread is run", "Time": "21-10-04 10:16:56"}, "52": {"location": "Bale Init", "result": "SendThread is run", "Time": "21-10-04 10:16:56"}, "53": {"location": "Main Open Thread", "result": "Connect", "Time": "21-10-04 10:17:00"}, "54": {"location": "Main Send Thread", "result": "Stop", "Time": "21-10-04 10:17:09"}, "55": {"location": "Main Open Thread", "result": "Stop", "Time": "21-10-04 10:17:20"}, "56": {"location": "Bale Init", "result": "OpenThread is run", "Time": "21-10-09 16:48:08"}, "57": {"location": "Bale Init", "result": "SendThread is run", "Time": "21-10-09 16:48:08"}, "58": {"location": "Main Open Thread", "result": "Connect", "Time": "21-10-09 16:48:15"}, "59": {"location": "Bale Init", "result": "OpenThread is run", "Time": "21-10-09 16:49:14"}, "60": {"location": "Bale Init", "result": "SendThread is run", "Time": "21-10-09 16:49:14"}, "61": {"location": "Main Open Thread", "result": "Connect", "Time": "21-10-09 16:49:25"}, "62": {"location": "Bale Init", "result": "OpenThread is run", "Time": "21-10-09 16:50:36"}, "63": {"location": "Bale Init", "result": "SendThread is run", "Time": "21-10-09 16:50:36"}, "64": {"location": "Main Open Thread", "result": "Connect", "Time": "21-10-09 16:50:38"}, "65": {"location": "Bale Init", "result": "OpenThread is run", "Time": "21-10-09 16:52:01"}, "66": {"location": "Bale Init", "result": "SendThread is run", "Time": "21-10-09 16:52:01"}, "67": {"location": "Main Open Thread", "result": "Connect", "Time": "21-10-09 16:52:06"}, "68": {"location": "Bale Init", "result": "OpenThread is run", "Time": "21-10-09 17:09:22"}, "69": {"location": "Bale Init", "result": "SendThread is run", "Time": "21-10-09 17:09:22"}, "70": {"location": "Main Open Thread", "result": "Connect", "Time": "21-10-09 17:09:28"}, "71": {"location": "Bale Init", "result": "OpenThread is run", "Time": "21-10-09 17:10:35"}, "72": {"location": "Bale Init", "result": "SendThread is run", "Time": "21-10-09 17:10:35"}, "73": {"location": "Main Open Thread", "result": "Connect", "Time": "21-10-09 17:10:35"}, "74": {"location": "Bale Init", "result": "OpenThread is run", "Time": "21-10-09 17:11:20"}, "75": {"location": "Bale Init", "result": "SendThread is run", "Time": "21-10-09 17:11:20"}, "76": {"location": "Main Open Thread", "result": "Connect", "Time": "21-10-09 17:11:22"}, "77": {"location": "Bale Init", "result": "OpenThread is run", "Time": "21-10-09 17:13:10"}, "78": {"location": "Bale Init", "result": "SendThread is run", "Time": "21-10-09 17:13:10"}, "79": {"location": "Main Open Thread", "result": "Connect", "Time": "21-10-09 17:13:20"}, "80": {"location": "Bale Init", "result": "OpenThread is run", "Time": "21-10-09 17:13:42"}, "81": {"location": "Bale Init", "result": "SendThread is run", "Time": "21-10-09 17:13:42"}, "82": {"location": "Main Open Thread", "result": "Connect", "Time": "21-10-09 17:13:48"}, "83": {"location": "Bale Init", "result": "OpenThread is run", "Time": "21-10-09 17:15:34"}, "84": {"location": "Bale Init", "result": "SendThread is run", "Time": "21-10-09 17:15:34"}, "85": {"location": "Main Open Thread", "result": "Connect", "Time": "21-10-09 17:15:35"}, "86": {"location": "Bale Init", "result": "OpenThread is run", "Time": "21-10-09 17:17:12"}, "87": {"location": "Bale Init", "result": "SendThread is run", "Time": "21-10-09 17:17:12"}, "88": {"location": "Bale Init", "result": "OpenThread is run", "Time": "21-10-09 17:17:58"}, "89": {"location": "Bale Init", "result": "SendThread is run", "Time": "21-10-09 17:17:58"}, "90": {"location": "Main Open Thread", "result": "Connect", "Time": "21-10-09 17:18:00"}, "91": {"location": "Main Send Thread", "result": "Stop", "Time": "21-10-09 17:19:02"}, "92": {"location": "Main Open Thread", "result": "Stop", "Time": "21-10-09 17:19:20"}, "93": {"location": "Bale Init", "result": "OpenThread is run", "Time": "21-10-09 17:21:05"}, "94": {"location": "Bale Init", "result": "SendThread is run", "Time": "21-10-09 17:21:05"}, "95": {"location": "Main Open Thread", "result": "Connect", "Time": "21-10-09 17:21:21"}, "96": {"location": "Bale Init", "result": "OpenThread is run", "Time": "21-10-09 17:22:55"}, "97": {"location": "Bale Init", "result": "SendThread is run", "Time": "21-10-09 17:22:55"}, "98": {"location": "Main Open Thread", "result": "Connect", "Time": "21-10-09 17:22:55"}, "99": {"location": "Bale Init", "result": "OpenThread is run", "Time": "21-10-09 17:23:05"}, "100": {"location": "Bale Init", "result": "SendThread is run", "Time": "21-10-09 17:23:05"}, "101": {"location": "Bale Init", "result": "OpenThread is run", "Time": "21-10-09 17:23:20"}, "102": {"location": "Bale Init", "result": "SendThread is run", "Time": "21-10-09 17:23:20"}, "103": {"location": "Main Open Thread", "result": "Connect", "Time": "21-10-09 17:23:21"}, "104": {"location": "Main Send Thread", "result": "Stop", "Time": "21-10-09 17:25:12"}, "105": {"location": "Main Open Thread", "result": "Stop", "Time": "21-10-09 17:25:21"}, "106": {"location": "Bale Init", "result": "OpenThread is run", "Time": "21-10-10 16:09:57"}, "107": {"location": "Bale Init", "result": "SendThread is run", "Time": "21-10-10 16:09:57"}, "108": {"location": "Main Open Thread", "result": "Connect", "Time": "21-10-10 16:09:58"}, "109": {"location": "Main Send Thread", "result": "Stop", "Time": "21-10-10 16:11:33"}, "110": {"location": "Main Open Thread", "result": "Stop", "Time": "21-10-10 16:11:38"}, "111": {"location": "Bale Init", "result": "OpenThread is run", "Time": "21-10-10 17:44:00"}, "112": {"location": "Bale Init", "result": "SendThread is run", "Time": "21-10-10 17:44:00"}, "113": {"location": "Main Open Thread", "result": "Connect", "Time": "21-10-10 17:44:01"}, "114": {"location": "Main Send Thread", "result": "Stop", "Time": "21-10-10 17:45:26"}, "115": {"location": "Main Open Thread", "result": "Stop", "Time": "21-10-10 17:45:41"}, "116": {"location": "Bale Init", "result": "OpenThread is run", "Time": "21-10-10 17:46:48"}, "117": {"location": "Bale Init", "result": "SendThread is run", "Time": "21-10-10 17:46:48"}, "118": {"location": "Main Open Thread", "result": "Connect", "Time": "21-10-10 17:46:49"}, "119": {"location": "Bale Init", "result": "OpenThread is run", "Time": "21-10-10 17:47:49"}, "120": {"location": "Bale Init", "result": "SendThread is run", "Time": "21-10-10 17:47:49"}, "121": {"location": "Main Open Thread", "result": "Connect", "Time": "21-10-10 17:47:49"}, "122": {"location": "Main Send Thread", "result": "Stop", "Time": "21-10-10 17:47:59"}, "123": {"location": "Main Open Thread", "result": "Stop", "Time": "21-10-10 17:48:09"}, "124": {"location": "Bale Init", "result": "OpenThread is run", "Time": "21-10-10 17:49:16"}, "125": {"location": "Bale Init", "result": "SendThread is run", "Time": "21-10-10 17:49:16"}, "126": {"location": "Main Open Thread", "result": "Connect", "Time": "21-10-10 17:49:17"}, "127": {"location": "Main Send Thread", "result": "Stop", "Time": "21-10-10 17:49:31"}, "128": {"location": "Main Open Thread", "result": "Stop", "Time": "21-10-10 17:49:37"}, "129": {"location": "Bale Init", "result": "OpenThread is run", "Time": "21-10-10 18:13:20"}, "130": {"location": "Bale Init", "result": "SendThread is run", "Time": "21-10-10 18:13:20"}, "131": {"location": "Main Open Thread", "result": "Connect", "Time": "21-10-10 18:13:21"}, "132": {"location": "Main Send Thread", "result": "Stop", "Time": "21-10-10 18:16:25"}, "133": {"location": "Main Open Thread", "result": "Stop", "Time": "21-10-10 18:16:42"}, "134": {"location": "Bale Init", "result": "OpenThread is run", "Time": "21-10-10 18:16:52"}, "135": {"location": "Bale Init", "result": "SendThread is run", "Time": "21-10-10 18:16:52"}, "136": {"location": "Main Open Thread", "result": "Connect", "Time": "21-10-10 18:16:53"}, "137": {"location": "Main Send Thread", "result": "Stop", "Time": "21-10-10 18:17:00"}, "138": {"location": "Main Open Thread", "result": "Stop", "Time": "21-10-10 18:17:13"}, "139": {"location": "Bale Init", "result": "OpenThread is run", "Time": "21-10-10 18:18:26"}, "140": {"location": "Bale Init", "result": "SendThread is run", "Time": "21-10-10 18:18:26"}, "141": {"location": "Main Open Thread", "result": "Connect", "Time": "21-10-10 18:18:27"}, "142": {"location": "Bale Init", "result": "OpenThread is run", "Time": "21-10-10 18:18:48"}, "143": {"location": "Bale Init", "result": "SendThread is run", "Time": "21-10-10 18:18:48"}, "144": {"location": "Main Open Thread", "result": "Connect", "Time": "21-10-10 18:18:48"}, "145": {"location": "Bale Init", "result": "OpenThread is run", "Time": "21-10-11 15:44:17"}, "146": {"location": "Bale Init", "result": "SendThread is run", "Time": "21-10-11 15:44:17"}, "147": {"location": "Main Open Thread", "result": "Connect", "Time": "21-10-11 15:44:18"}, "148": {"location": "Bale Init", "result": "OpenThread is run", "Time": "21-10-11 15:44:48"}, "149": {"location": "Bale Init", "result": "SendThread is run", "Time": "21-10-11 15:44:49"}, "150": {"location": "Main Open Thread", "result": "Connect", "Time": "21-10-11 15:44:49"}, "151": {"location": "Main Send Thread", "result": "Stop", "Time": "21-10-11 15:45:13"}, "152": {"location": "Main Open Thread", "result": "Stop", "Time": "21-10-11 15:45:29"}, "153": {"location": "Bale Init", "result": "OpenThread is run", "Time": "21-10-11 15:51:14"}, "154": {"location": "Bale Init", "result": "SendThread is run", "Time": "21-10-11 15:51:14"}, "155": {"location": "Main Open Thread", "result": "Connect", "Time": "21-10-11 15:51:14"}, "156": {"location": "Main Send Thread", "result": "Stop", "Time": "21-10-11 15:51:38"}, "157": {"location": "Main Open Thread", "result": "Stop", "Time": "21-10-11 15:51:54"}, "158": {"location": "Bale Init", "result": "OpenThread is run", "Time": "21-10-11 15:55:22"}, "159": {"location": "Bale Init", "result": "SendThread is run", "Time": "21-10-11 15:55:22"}, "160": {"location": "Main Open Thread", "result": "Connect", "Time": "21-10-11 15:55:22"}, "161": {"location": "Main Send Thread", "result": "Stop", "Time": "21-10-11 16:00:46"}, "162": {"location": "Main Open Thread", "result": "Stop", "Time": "21-10-11 16:01:02"}, "163": {"location": "Bale Init", "result": "OpenThread is run", "Time": "21-10-11 16:19:36"}, "164": {"location": "Bale Init", "result": "SendThread is run", "Time": "21-10-11 16:19:36"}, "165": {"location": "Main Open Thread", "result": "Connect", "Time": "21-10-11 16:19:37"}, "166": {"location": "Main Send Thread", "result": "Stop", "Time": "21-10-11 16:19:47"}, "167": {"location": "Main Open Thread", "result": "Stop", "Time": "21-10-11 16:19:58"}}, "Sender": {"1": {"location": "Run Thread", "result": "Thread is run", "Time": "21-10-04 09:48:49"}, "2": {"location": "Run Thread", "result": "Thread is run", "Time": "21-10-04 09:48:49"}, "3": {"location": "Main Sender Thread", "result": "Stop", "Time": "21-10-04 09:49:06"}, "4": {"location": "Run Thread", "result": "Thread is run", "Time": "21-10-04 09:49:48"}, "5": {"location": "Run Thread", "result": "Thread is run", "Time": "21-10-04 09:49:48"}, "6": {"location": "Main Sender Thread", "result": "Stop", "Time": "21-10-04 09:50:12"}, "7": {"location": "Run Thread", "result": "Thread is run", "Time": "21-10-04 09:51:57"}, "8": {"location": "Run Thread", "result": "Thread is run", "Time": "21-10-04 09:51:57"}, "9": {"location": "Run Thread", "result": "Thread is run", "Time": "21-10-04 09:59:26"}, "10": {"location": "Run Thread", "result": "Thread is run", "Time": "21-10-04 09:59:26"}, "11": {"location": "Run Thread", "result": "Thread is run", "Time": "21-10-04 10:02:30"}, "12": {"location": "Run Thread", "result": "Thread is run", "Time": "21-10-04 10:02:30"}, "13": {"location": "Run Thread", "result": "Thread is run", "Time": "21-10-04 10:04:06"}, "14": {"location": "Run Thread", "result": "Thread is run", "Time": "21-10-04 10:04:06"}, "15": {"location": "Main Sender Thread", "result": "Stop", "Time": "21-10-04 10:04:25"}, "16": {"location": "Run Thread", "result": "Thread is run", "Time": "21-10-04 10:11:26"}, "17": {"location": "Run Thread", "result": "Thread is run", "Time": "21-10-04 10:11:26"}, "18": {"location": "Main Sender Thread", "result": "Stop", "Time": "21-10-04 10:11:45"}, "19": {"location": "Run Thread", "result": "Thread is run", "Time": "21-10-04 10:12:21"}, "20": {"location": "Run Thread", "result": "Thread is run", "Time": "21-10-04 10:12:22"}, "21": {"location": "Main Sender Thread", "result": "Stop", "Time": "21-10-04 10:12:47"}, "22": {"location": "Run Thread", "result": "Thread is run", "Time": "21-10-04 10:14:43"}, "23": {"location": "Run Thread", "result": "Thread is run", "Time": "21-10-04 10:14:43"}, "24": {"location": "Main Sender Thread", "result": "Stop", "Time": "21-10-04 10:15:01"}, "25": {"location": "Run Thread", "result": "Thread is run", "Time": "21-10-04 10:16:05"}, "26": {"location": "Run Thread", "result": "Thread is run", "Time": "21-10-04 10:16:05"}, "27": {"location": "Main Sender Thread", "result": "Stop", "Time": "21-10-04 10:16:44"}, "28": {"location": "Run Thread", "result": "Thread is run", "Time": "21-10-04 10:16:59"}, "29": {"location": "Run Thread", "result": "Thread is run", "Time": "21-10-04 10:16:59"}, "30": {"location": "Main Sender Thread", "result": "Stop", "Time": "21-10-04 10:17:21"}, "31": {"location": "Run Thread", "result": "Thread is run", "Time": "21-10-09 16:48:10"}, "32": {"location": "Run Thread", "result": "Thread is run", "Time": "21-10-09 16:49:16"}, "33": {"location": "Run Thread", "result": "Thread is run", "Time": "21-10-09 16:50:39"}, "34": {"location": "Run Thread", "result": "Thread is run", "Time": "21-10-09 16:52:03"}, "35": {"location": "Run Thread", "result": "Thread is run", "Time": "21-10-09 17:09:24"}, "36": {"location": "Run Thread", "result": "Thread is run", "Time": "21-10-09 17:10:37"}, "37": {"location": "Run Thread", "result": "Thread is run", "Time": "21-10-09 17:13:45"}, "38": {"location": "Run Thread", "result": "Thread is run", "Time": "21-10-09 17:15:36"}, "39": {"location": "Run Thread", "result": "Thread is run", "Time": "21-10-09 17:17:14"}, "40": {"location": "Run Thread", "result": "Thread is run", "Time": "21-10-09 17:18:00"}, "41": {"location": "Run Thread", "result": "Thread is run", "Time": "21-10-09 17:21:07"}, "42": {"location": "Run Thread", "result": "Thread is run", "Time": "21-10-09 17:23:07"}, "43": {"location": "Run Thread", "result": "Thread is run", "Time": "21-10-09 17:23:23"}, "44": {"location": "Run Thread", "result": "Thread is run", "Time": "21-10-10 16:09:59"}, "45": {"location": "Run Thread", "result": "Thread is run", "Time": "21-10-10 17:44:02"}, "46": {"location": "Run Thread", "result": "Thread is run", "Time": "21-10-10 17:46:50"}, "47": {"location": "Run Thread", "result": "Thread is run", "Time": "21-10-10 17:47:51"}, "48": {"location": "Run Thread", "result": "Thread is run", "Time": "21-10-10 17:49:19"}, "49": {"location": "Run Thread", "result": "Thread is run", "Time": "21-10-10 18:13:22"}, "50": {"location": "Run Thread", "result": "Thread is run", "Time": "21-10-10 18:16:54"}, "51": {"location": "Run Thread", "result": "Thread is run", "Time": "21-10-10 18:18:28"}, "52": {"location": "Run Thread", "result": "Thread is run", "Time": "21-10-10 18:18:50"}, "53": {"location": "Run Thread", "result": "Thread is run", "Time": "21-10-11 15:44:51"}, "54": {"location": "Run Thread", "result": "Thread is run", "Time": "21-10-11 15:51:16"}, "55": {"location": "Run Thread", "result": "Thread is run", "Time": "21-10-11 15:55:24"}, "56": {"location": "Run Thread", "result": "Thread is run", "Time": "21-10-11 16:19:38"}}, "DA": {"1": {"location": "Init PLC test", "result": "PLC test start", "Time": "21-10-09 17:13:45"}, "2": {"location": "Init PLC test", "result": "PLC test start", "Time": "21-10-09 17:15:36"}, "3": {"location": "Init PLC test", "result": "PLC test start", "Time": "21-10-09 17:17:14"}, "4": {"location": "Init PLC test", "result": "PLC test start", "Time": "21-10-09 17:18:00"}, "5": {"location": "Reading Data Thread test", "result": "PLC test Stop", "Time": "21-10-09 17:19:25"}, "6": {"location": "Init PLC test", "result": "PLC test start", "Time": "21-10-09 17:21:07"}, "7": {"location": "Init PLC test", "result": "PLC test start", "Time": "21-10-09 17:23:07"}, "8": {"location": "Init PLC test", "result": "PLC test start", "Time": "21-10-09 17:23:23"}, "9": {"location": "Reading Data Thread test", "result": "PLC test Stop", "Time": "21-10-09 17:25:25"}, "10": {"location": "Init PLC test", "result": "PLC test start", "Time": "21-10-10 16:09:59"}, "11": {"location": "Reading Data Thread test", "result": "PLC test Stop", "Time": "21-10-10 16:11:43"}, "12": {"location": "Init PLC test", "result": "PLC test start", "Time": "21-10-10 17:44:02"}, "13": {"location": "Reading Data Thread test", "result": "PLC test Stop", "Time": "21-10-10 17:45:47"}, "14": {"location": "Init PLC test", "result": "PLC test start", "Time": "21-10-10 17:46:50"}, "15": {"location": "Init PLC test", "result": "PLC test start", "Time": "21-10-10 17:47:51"}, "16": {"location": "Reading Data Thread test", "result": "PLC test Stop", "Time": "21-10-10 17:48:14"}, "17": {"location": "Init PLC test", "result": "PLC test start", "Time": "21-10-10 17:49:19"}, "18": {"location": "Reading Data Thread test", "result": "PLC test Stop", "Time": "21-10-10 17:49:42"}, "19": {"location": "Init PLC test", "result": "PLC test start", "Time": "21-10-10 18:13:22"}, "20": {"location": "Reading Data Thread test", "result": "PLC test Stop", "Time": "21-10-10 18:16:46"}, "21": {"location": "Init PLC test", "result": "PLC test start", "Time": "21-10-10 18:16:54"}, "22": {"location": "Reading Data Thread test", "result": "PLC test Stop", "Time": "21-10-10 18:17:17"}, "23": {"location": "Init PLC test", "result": "PLC test start", "Time": "21-10-10 18:18:28"}, "24": {"location": "Init PLC test", "result": "PLC test start", "Time": "21-10-10 18:18:50"}, "25": {"location": "Init PLC test", "result": "PLC test start", "Time": "21-10-11 15:44:19"}, "26": {"location": "Init PLC test", "result": "PLC test start", "Time": "21-10-11 15:44:51"}, "27": {"location": "Reading Data Thread test", "result": "PLC test Stop", "Time": "21-10-11 15:45:35"}, "28": {"location": "Init PLC test", "result": "PLC test start", "Time": "21-10-11 15:51:16"}, "29": {"location": "Reading Data Thread test", "result": "PLC test Stop", "Time": "21-10-11 15:52:00"}, "30": {"location": "Init PLC test", "result": "PLC test start", "Time": "21-10-11 15:55:24"}, "31": {"location": "Reading Data Thread test", "result": "PLC test Stop", "Time": "21-10-11 16:01:09"}, "32": {"location": "Init PLC test", "result": "PLC test start", "Time": "21-10-11 16:19:38"}, "33": {"location": "Reading Data Thread test", "result": "PLC test Stop", "Time": "21-10-11 16:20:12"}}}